[
    {
        "episode_id": "c4151afd-eaea-11eb-8e3e-8cc84b59ec7a",
        "anime_url": "https://gum-gum-streaming.com/visions-descaflowne-vostfr/",
        "episode_name": "• Épisode 1: La promesse du destin",
        "episode_url": "https://gum-gum-streaming.com/visions-descaflowne-1-vostfr/"
    },
    {
        "episode_id": "c4182e5f-eaea-11eb-a468-8cc84b59ec7a",
        "anime_url": "https://gum-gum-streaming.com/visions-descaflowne-vostfr/",
        "episode_name": "• Épisode 2: La fille de la lune des illusions",
        "episode_url": "https://gum-gum-streaming.com/visions-descaflowne-2-vostfr/"
    },
    {
        "episode_id": "c41aed16-eaea-11eb-a2b0-8cc84b59ec7a",
        "anime_url": "https://gum-gum-streaming.com/visions-descaflowne-vostfr/",
        "episode_name": "• Épisode 3: Le guerrier magnifique",
        "episode_url": "https://gum-gum-streaming.com/visions-descaflowne-3-vostfr/"
    },
    {
        "episode_id": "c41dd34e-eaea-11eb-a762-8cc84b59ec7a",
        "anime_url": "https://gum-gum-streaming.com/visions-descaflowne-vostfr/",
        "episode_name": "• Épisode 4: Un garçon diabolique",
        "episode_url": "https://gum-gum-streaming.com/visions-descaflowne-4-vostfr/"
    },
    {
        "episode_id": "c420b9af-eaea-11eb-8bfe-8cc84b59ec7a",
        "anime_url": "https://gum-gum-streaming.com/visions-descaflowne-vostfr/",
        "episode_name": "• Épisode 5: Le sceau de la fraternité",
        "episode_url": "https://gum-gum-streaming.com/visions-descaflowne-5-vostfr/"
    },
    {
        "episode_id": "c423a0d1-eaea-11eb-b666-8cc84b59ec7a",
        "anime_url": "https://gum-gum-streaming.com/visions-descaflowne-vostfr/",
        "episode_name": "• Épisode 6: La cité des intrigues",
        "episode_url": "https://gum-gum-streaming.com/visions-descaflowne-6-vostfr/"
    },
    {
        "episode_id": "c4272388-eaea-11eb-be81-8cc84b59ec7a",
        "anime_url": "https://gum-gum-streaming.com/visions-descaflowne-vostfr/",
        "episode_name": "• Épisode 7: Séparation imprévue",
        "episode_url": "https://gum-gum-streaming.com/visions-descaflowne-7-vostfr/"
    },
    {
        "episode_id": "c42a30f3-eaea-11eb-896f-8cc84b59ec7a",
        "anime_url": "https://gum-gum-streaming.com/visions-descaflowne-vostfr/",
        "episode_name": "• Épisode 8: Le jour de la danse de l’ange",
        "episode_url": "https://gum-gum-streaming.com/visions-descaflowne-8-vostfr/"
    },
    {
        "episode_id": "c4399a71-eaea-11eb-b1ad-8cc84b59ec7a",
        "anime_url": "https://gum-gum-streaming.com/visions-descaflowne-vostfr/",
        "episode_name": "• Épisode 9: Les ailes de la mémoire",
        "episode_url": "https://gum-gum-streaming.com/visions-descaflowne-9-vostfr/"
    },
    {
        "episode_id": "c43fb535-eaea-11eb-88c8-8cc84b59ec7a",
        "anime_url": "https://gum-gum-streaming.com/visions-descaflowne-vostfr/",
        "episode_name": "• Épisode 10: Le prince aux yeux bleus",
        "episode_url": "https://gum-gum-streaming.com/visions-descaflowne-10-vostfr/"
    },
    {
        "episode_id": "c4448f56-eaea-11eb-9b42-8cc84b59ec7a",
        "anime_url": "https://gum-gum-streaming.com/visions-descaflowne-vostfr/",
        "episode_name": "• Épisode 11: Prédiction mortelle",
        "episode_url": "https://gum-gum-streaming.com/visions-descaflowne-11-vostfr/"
    },
    {
        "episode_id": "c44a347e-eaea-11eb-aabc-8cc84b59ec7a",
        "anime_url": "https://gum-gum-streaming.com/visions-descaflowne-vostfr/",
        "episode_name": "• Épisode 12: La porte aux secrets",
        "episode_url": "https://gum-gum-streaming.com/visions-descaflowne-12-vostfr/"
    },
    {
        "episode_id": "c4517639-eaea-11eb-9abe-8cc84b59ec7a",
        "anime_url": "https://gum-gum-streaming.com/visions-descaflowne-vostfr/",
        "episode_name": "• Épisode 13: Le fil rouge du destin",
        "episode_url": "https://gum-gum-streaming.com/visions-descaflowne-13-vostfr/"
    },
    {
        "episode_id": "c456dcd9-eaea-11eb-85e4-8cc84b59ec7a",
        "anime_url": "https://gum-gum-streaming.com/visions-descaflowne-vostfr/",
        "episode_name": "• Épisode 14: La cicatrice du danger",
        "episode_url": "https://gum-gum-streaming.com/visions-descaflowne-14-vostfr/"
    },
    {
        "episode_id": "c459c324-eaea-11eb-a082-8cc84b59ec7a",
        "anime_url": "https://gum-gum-streaming.com/visions-descaflowne-vostfr/",
        "episode_name": "• Épisode 15: Paradis perdu",
        "episode_url": "https://gum-gum-streaming.com/visions-descaflowne-15-vostfr/"
    },
    {
        "episode_id": "c45d1ea3-eaea-11eb-9a3c-8cc84b59ec7a",
        "anime_url": "https://gum-gum-streaming.com/visions-descaflowne-vostfr/",
        "episode_name": "• Épisode 16: Les guides",
        "episode_url": "https://gum-gum-streaming.com/visions-descaflowne-16-vostfr/"
    },
    {
        "episode_id": "c460a161-eaea-11eb-8e6f-8cc84b59ec7a",
        "anime_url": "https://gum-gum-streaming.com/visions-descaflowne-vostfr/",
        "episode_name": "• Épisode 17: Jusqu’au bout du monde",
        "episode_url": "https://gum-gum-streaming.com/visions-descaflowne-17-vostfr/"
    },
    {
        "episode_id": "c4648fe5-eaea-11eb-9965-8cc84b59ec7a",
        "anime_url": "https://gum-gum-streaming.com/visions-descaflowne-vostfr/",
        "episode_name": "• Épisode 18: La puissance du destin",
        "episode_url": "https://gum-gum-streaming.com/visions-descaflowne-18-vostfr/"
    },
    {
        "episode_id": "c468128a-eaea-11eb-baa1-8cc84b59ec7a",
        "anime_url": "https://gum-gum-streaming.com/visions-descaflowne-vostfr/",
        "episode_name": "• Épisode 19: La règle d’or de l’amour",
        "episode_url": "https://gum-gum-streaming.com/visions-descaflowne-19-vostfr/"
    },
    {
        "episode_id": "c46b9573-eaea-11eb-b7a1-8cc84b59ec7a",
        "anime_url": "https://gum-gum-streaming.com/visions-descaflowne-vostfr/",
        "episode_name": "• Épisode 20: Le serment du mensonge",
        "episode_url": "https://gum-gum-streaming.com/visions-descaflowne-20-vostfr/"
    },
    {
        "episode_id": "c46f3ee1-eaea-11eb-8a30-8cc84b59ec7a",
        "anime_url": "https://gum-gum-streaming.com/visions-descaflowne-vostfr/",
        "episode_name": "• Épisode 21: Les revers du destin",
        "episode_url": "https://gum-gum-streaming.com/visions-descaflowne-21-vostfr/"
    },
    {
        "episode_id": "c4729a74-eaea-11eb-9a14-8cc84b59ec7a",
        "anime_url": "https://gum-gum-streaming.com/visions-descaflowne-vostfr/",
        "episode_name": "• Épisode 22: L’ange aux ailes ténébreuses",
        "episode_url": "https://gum-gum-streaming.com/visions-descaflowne-22-vostfr/"
    },
    {
        "episode_id": "c476e074-eaea-11eb-9336-8cc84b59ec7a",
        "anime_url": "https://gum-gum-streaming.com/visions-descaflowne-vostfr/",
        "episode_name": "• Épisode 23: Prélude à la tempête",
        "episode_url": "https://gum-gum-streaming.com/visions-descaflowne-23-vostfr/"
    },
    {
        "episode_id": "c47a8a39-eaea-11eb-b456-8cc84b59ec7a",
        "anime_url": "https://gum-gum-streaming.com/visions-descaflowne-vostfr/",
        "episode_name": "• Épisode 24: Le choix d’un destin",
        "episode_url": "https://gum-gum-streaming.com/visions-descaflowne-24-vostfr/"
    },
    {
        "episode_id": "c47e33e0-eaea-11eb-b63d-8cc84b59ec7a",
        "anime_url": "https://gum-gum-streaming.com/visions-descaflowne-vostfr/",
        "episode_name": "• Épisode 25: La sphère du bonheur absolu",
        "episode_url": "https://gum-gum-streaming.com/visions-descaflowne-25-vostfr/"
    },
    {
        "episode_id": "c481b696-eaea-11eb-ae35-8cc84b59ec7a",
        "anime_url": "https://gum-gum-streaming.com/visions-descaflowne-vostfr/",
        "episode_name": "• Épisode 26: Un souvenir éternel",
        "episode_url": "https://gum-gum-streaming.com/visions-descaflowne-26-vostfr/"
    },
    {
        "episode_id": "c48c175d-eaea-11eb-a127-8cc84b59ec7a",
        "anime_url": "https://gum-gum-streaming.com/visions-descaflowne-vostfr/",
        "episode_name": "• Film 1: Une fille sur Gaïa",
        "episode_url": "https://gum-gum-streaming.com/visions-descaflowne-film-1-vostfr/"
    }
]