[
    {
        "episode_id": "fab85f2f-eaef-11eb-8a48-8cc84b59ec7a",
        "anime_url": "https://gum-gum-streaming.com/goblin-slayer-vf/",
        "episode_name": "• Épisode 1: Le Sort de quelques aventuriers",
        "episode_url": "https://gum-gum-streaming.com/goblin-slayer-1-vf/"
    },
    {
        "episode_id": "fabbe1b4-eaef-11eb-996c-8cc84b59ec7a",
        "anime_url": "https://gum-gum-streaming.com/goblin-slayer-vf/",
        "episode_name": "• Épisode 2: Le Tueur de petits démons",
        "episode_url": "https://gum-gum-streaming.com/goblin-slayer-2-vf/"
    },
    {
        "episode_id": "fabf6457-eaef-11eb-be22-8cc84b59ec7a",
        "anime_url": "https://gum-gum-streaming.com/goblin-slayer-vf/",
        "episode_name": "• Épisode 3: Des visiteurs inattendus",
        "episode_url": "https://gum-gum-streaming.com/goblin-slayer-3-vf/"
    },
    {
        "episode_id": "fac2dbe7-eaef-11eb-8bdd-8cc84b59ec7a",
        "anime_url": "https://gum-gum-streaming.com/goblin-slayer-vf/",
        "episode_name": "• Épisode 4: Les Puissants",
        "episode_url": "https://gum-gum-streaming.com/goblin-slayer-4-vf/"
    },
    {
        "episode_id": "fac64348-eaef-11eb-9f14-8cc84b59ec7a",
        "anime_url": "https://gum-gum-streaming.com/goblin-slayer-vf/",
        "episode_name": "• Épisode 5: Aventures et quotidien",
        "episode_url": "https://gum-gum-streaming.com/goblin-slayer-5-vf/"
    },
    {
        "episode_id": "fac9b97c-eaef-11eb-8763-8cc84b59ec7a",
        "anime_url": "https://gum-gum-streaming.com/goblin-slayer-vf/",
        "episode_name": "• Épisode 6: Extermination à la ville des eaux",
        "episode_url": "https://gum-gum-streaming.com/goblin-slayer-6-vf/"
    },
    {
        "episode_id": "facd2fdd-eaef-11eb-8487-8cc84b59ec7a",
        "anime_url": "https://gum-gum-streaming.com/goblin-slayer-vf/",
        "episode_name": "• Épisode 7: Jusqu’à la mort",
        "episode_url": "https://gum-gum-streaming.com/goblin-slayer-7-vf/"
    },
    {
        "episode_id": "fad0a4bf-eaef-11eb-a41c-8cc84b59ec7a",
        "anime_url": "https://gum-gum-streaming.com/goblin-slayer-vf/",
        "episode_name": "• Épisode 8: Murmures, prières et chants",
        "episode_url": "https://gum-gum-streaming.com/goblin-slayer-8-vf/"
    },
    {
        "episode_id": "fad3f4b5-eaef-11eb-8f78-8cc84b59ec7a",
        "anime_url": "https://gum-gum-streaming.com/goblin-slayer-vf/",
        "episode_name": "• Épisode 9: Un aller et un retour",
        "episode_url": "https://gum-gum-streaming.com/goblin-slayer-9-vf/"
    },
    {
        "episode_id": "fad775f1-eaef-11eb-85bc-8cc84b59ec7a",
        "anime_url": "https://gum-gum-streaming.com/goblin-slayer-vf/",
        "episode_name": "• Épisode 10: Somnolence",
        "episode_url": "https://gum-gum-streaming.com/goblin-slayer-10-vf/"
    },
    {
        "episode_id": "fadad7f5-eaef-11eb-83f9-8cc84b59ec7a",
        "anime_url": "https://gum-gum-streaming.com/goblin-slayer-vf/",
        "episode_name": "• Épisode 11: Le Banquet des aventuriers",
        "episode_url": "https://gum-gum-streaming.com/goblin-slayer-11-vf/"
    },
    {
        "episode_id": "fadf0118-eaef-11eb-9d47-8cc84b59ec7a",
        "anime_url": "https://gum-gum-streaming.com/goblin-slayer-vf/",
        "episode_name": "• Épisode 12: Le Sort d’un aventurier",
        "episode_url": "https://gum-gum-streaming.com/goblin-slayer-12-vf/"
    },
    {
        "episode_id": "fae62246-eaef-11eb-bd70-8cc84b59ec7a",
        "anime_url": "https://gum-gum-streaming.com/goblin-slayer-vf/",
        "episode_name": "• Film 1: Goblin’s Crown",
        "episode_url": "https://gum-gum-streaming.com/goblin-slayer-film-1-vf/"
    }
]