[
    {
        "episode_id": "c0854d59-eaf3-11eb-8eb3-8cc84b59ec7a",
        "anime_url": "https://gum-gum-streaming.com/vandread-vf/",
        "episode_name": "• Épisode 1: Première rencontre",
        "episode_url": "https://gum-gum-streaming.com/vandread-1-vf/"
    },
    {
        "episode_id": "c0896c43-eaf3-11eb-a7d7-8cc84b59ec7a",
        "anime_url": "https://gum-gum-streaming.com/vandread-vf/",
        "episode_name": "• Épisode 2: Je me suis perdu",
        "episode_url": "https://gum-gum-streaming.com/vandread-2-vf/"
    },
    {
        "episode_id": "c08d548f-eaf3-11eb-9217-8cc84b59ec7a",
        "anime_url": "https://gum-gum-streaming.com/vandread-vf/",
        "episode_name": "• Épisode 3: La voie que j’ai choisie",
        "episode_url": "https://gum-gum-streaming.com/vandread-3-vf/"
    },
    {
        "episode_id": "c0915597-eaf3-11eb-88e3-8cc84b59ec7a",
        "anime_url": "https://gum-gum-streaming.com/vandread-vf/",
        "episode_name": "• Épisode 4: Je veux tout savoir sur toi",
        "episode_url": "https://gum-gum-streaming.com/vandread-4-vf/"
    },
    {
        "episode_id": "c0954d87-eaf3-11eb-8e22-8cc84b59ec7a",
        "anime_url": "https://gum-gum-streaming.com/vandread-vf/",
        "episode_name": "• Épisode 5: Piégés par les sables",
        "episode_url": "https://gum-gum-streaming.com/vandread-5-vf/"
    },
    {
        "episode_id": "c09a455e-eaf3-11eb-8d61-8cc84b59ec7a",
        "anime_url": "https://gum-gum-streaming.com/vandread-vf/",
        "episode_name": "• Épisode 6: Quel monde merveilleux",
        "episode_url": "https://gum-gum-streaming.com/vandread-6-vf/"
    },
    {
        "episode_id": "c09e3d31-eaf3-11eb-9b9d-8cc84b59ec7a",
        "anime_url": "https://gum-gum-streaming.com/vandread-vf/",
        "episode_name": "• Épisode 7: La vie facile",
        "episode_url": "https://gum-gum-streaming.com/vandread-7-vf/"
    },
    {
        "episode_id": "c0a283af-eaf3-11eb-afb1-8cc84b59ec7a",
        "anime_url": "https://gum-gum-streaming.com/vandread-vf/",
        "episode_name": "• Épisode 8: Impossible!",
        "episode_url": "https://gum-gum-streaming.com/vandread-8-vf/"
    },
    {
        "episode_id": "c0a71772-eaf3-11eb-8c72-8cc84b59ec7a",
        "anime_url": "https://gum-gum-streaming.com/vandread-vf/",
        "episode_name": "• Épisode 9: L’enfer n’est pas ici",
        "episode_url": "https://gum-gum-streaming.com/vandread-9-vf/"
    },
    {
        "episode_id": "c0ab104a-eaf3-11eb-8648-8cc84b59ec7a",
        "anime_url": "https://gum-gum-streaming.com/vandread-vf/",
        "episode_name": "• Épisode 10: Un amour blanc",
        "episode_url": "https://gum-gum-streaming.com/vandread-10-vf/"
    },
    {
        "episode_id": "c0af0826-eaf3-11eb-882b-8cc84b59ec7a",
        "anime_url": "https://gum-gum-streaming.com/vandread-vf/",
        "episode_name": "• Épisode 11: Pour elle",
        "episode_url": "https://gum-gum-streaming.com/vandread-11-vf/"
    },
    {
        "episode_id": "c0b2d926-eaf3-11eb-a830-8cc84b59ec7a",
        "anime_url": "https://gum-gum-streaming.com/vandread-vf/",
        "episode_name": "• Épisode 12: L’indifférence peut tuer",
        "episode_url": "https://gum-gum-streaming.com/vandread-12-vf/"
    },
    {
        "episode_id": "c0b6d0bb-eaf3-11eb-8fd1-8cc84b59ec7a",
        "anime_url": "https://gum-gum-streaming.com/vandread-vf/",
        "episode_name": "• Épisode 13: Le souffle du feu",
        "episode_url": "https://gum-gum-streaming.com/vandread-13-vf/"
    },
    {
        "episode_id": "c0c09559-eaf3-11eb-811d-8cc84b59ec7a",
        "anime_url": "https://gum-gum-streaming.com/vandread-vf/",
        "episode_name": "• Épisode 14: Le rayon rouge",
        "episode_url": "https://gum-gum-streaming.com/vandread-14-vf/"
    },
    {
        "episode_id": "c0c4da9b-eaf3-11eb-9ed7-8cc84b59ec7a",
        "anime_url": "https://gum-gum-streaming.com/vandread-vf/",
        "episode_name": "• Épisode 15: Le message",
        "episode_url": "https://gum-gum-streaming.com/vandread-15-vf/"
    },
    {
        "episode_id": "c0c8f984-eaf3-11eb-9f1d-8cc84b59ec7a",
        "anime_url": "https://gum-gum-streaming.com/vandread-vf/",
        "episode_name": "• Épisode 16: Un peu de tendresse",
        "episode_url": "https://gum-gum-streaming.com/vandread-16-vf/"
    },
    {
        "episode_id": "c0cd1921-eaf3-11eb-9c2e-8cc84b59ec7a",
        "anime_url": "https://gum-gum-streaming.com/vandread-vf/",
        "episode_name": "• Épisode 17: Tout, tout et tout",
        "episode_url": "https://gum-gum-streaming.com/vandread-17-vf/"
    },
    {
        "episode_id": "c0d0e92b-eaf3-11eb-9120-8cc84b59ec7a",
        "anime_url": "https://gum-gum-streaming.com/vandread-vf/",
        "episode_name": "• Épisode 18: Une grande tristesse",
        "episode_url": "https://gum-gum-streaming.com/vandread-18-vf/"
    },
    {
        "episode_id": "c0d493a0-eaf3-11eb-948e-8cc84b59ec7a",
        "anime_url": "https://gum-gum-streaming.com/vandread-vf/",
        "episode_name": "• Épisode 19: La vie continue",
        "episode_url": "https://gum-gum-streaming.com/vandread-19-vf/"
    },
    {
        "episode_id": "c0d7ee74-eaf3-11eb-877f-8cc84b59ec7a",
        "anime_url": "https://gum-gum-streaming.com/vandread-vf/",
        "episode_name": "• Épisode 20: Un choix difficile",
        "episode_url": "https://gum-gum-streaming.com/vandread-20-vf/"
    },
    {
        "episode_id": "c0db71d6-eaf3-11eb-b162-8cc84b59ec7a",
        "anime_url": "https://gum-gum-streaming.com/vandread-vf/",
        "episode_name": "• Épisode 21: La réalité",
        "episode_url": "https://gum-gum-streaming.com/vandread-21-vf/"
    },
    {
        "episode_id": "c0def3c7-eaf3-11eb-baee-8cc84b59ec7a",
        "anime_url": "https://gum-gum-streaming.com/vandread-vf/",
        "episode_name": "• Épisode 22: La caverne des esprits",
        "episode_url": "https://gum-gum-streaming.com/vandread-22-vf/"
    },
    {
        "episode_id": "c0e24f63-eaf3-11eb-a700-8cc84b59ec7a",
        "anime_url": "https://gum-gum-streaming.com/vandread-vf/",
        "episode_name": "• Épisode 23: Sur le chemin du retour",
        "episode_url": "https://gum-gum-streaming.com/vandread-23-vf/"
    },
    {
        "episode_id": "c0e5d1f5-eaf3-11eb-ac98-8cc84b59ec7a",
        "anime_url": "https://gum-gum-streaming.com/vandread-vf/",
        "episode_name": "• Épisode 24: Le paradis",
        "episode_url": "https://gum-gum-streaming.com/vandread-24-vf/"
    },
    {
        "episode_id": "c0e92d93-eaf3-11eb-8965-8cc84b59ec7a",
        "anime_url": "https://gum-gum-streaming.com/vandread-vf/",
        "episode_name": "• Épisode 25: L’heure de vérité",
        "episode_url": "https://gum-gum-streaming.com/vandread-25-vf/"
    },
    {
        "episode_id": "c0ecb0e5-eaf3-11eb-b1da-8cc84b59ec7a",
        "anime_url": "https://gum-gum-streaming.com/vandread-vf/",
        "episode_name": "• Épisode 26: Une confiance totale",
        "episode_url": "https://gum-gum-streaming.com/vandread-26-vf/"
    },
    {
        "episode_id": "c0f3f8fe-eaf3-11eb-b5cf-8cc84b59ec7a",
        "anime_url": "https://gum-gum-streaming.com/vandread-vf/",
        "episode_name": "• OAV 1: Vandread Integral",
        "episode_url": "https://gum-gum-streaming.com/vandread-oav-1-vostfr/"
    },
    {
        "episode_id": "c0f78107-eaf3-11eb-9b01-8cc84b59ec7a",
        "anime_url": "https://gum-gum-streaming.com/vandread-vf/",
        "episode_name": "• OAV 2: Vandread Turbulence",
        "episode_url": "https://gum-gum-streaming.com/vandread-oav-2-vostfr/"
    }
]