[
    {
        "episode_id": "bbb447ef-ea96-11eb-ba63-8cc84b59ec7a",
        "anime_url": "https://gum-gum-streaming.com/eyeshield-21-vostfr/",
        "episode_name": "• Épisode 1: L’homme aux jambes rapides comme la lumière",
        "episode_url": "https://gum-gum-streaming.com/eyeshield-21-1-vostfr/"
    },
    {
        "episode_id": "bbb8102a-ea96-11eb-bd21-8cc84b59ec7a",
        "anime_url": "https://gum-gum-streaming.com/eyeshield-21-vostfr/",
        "episode_name": "• Épisode 2: Jouons au football américain!",
        "episode_url": "https://gum-gum-streaming.com/eyeshield-21-2-vostfr/"
    },
    {
        "episode_id": "bbbbb92a-ea96-11eb-a916-8cc84b59ec7a",
        "anime_url": "https://gum-gum-streaming.com/eyeshield-21-vostfr/",
        "episode_name": "• Épisode 3: Écrase le terrain!",
        "episode_url": "https://gum-gum-streaming.com/eyeshield-21-3-vostfr/"
    },
    {
        "episode_id": "bbbf62ee-ea96-11eb-af83-8cc84b59ec7a",
        "anime_url": "https://gum-gum-streaming.com/eyeshield-21-vostfr/",
        "episode_name": "• Épisode 4: Ce qu’on peut attraper de la main",
        "episode_url": "https://gum-gum-streaming.com/eyeshield-21-4-vostfr/"
    },
    {
        "episode_id": "bbc30ca4-ea96-11eb-a81d-8cc84b59ec7a",
        "anime_url": "https://gum-gum-streaming.com/eyeshield-21-vostfr/",
        "episode_name": "• Épisode 5: Gardes du corps durant une demi-seconde",
        "episode_url": "https://gum-gum-streaming.com/eyeshield-21-5-vostfr/"
    },
    {
        "episode_id": "bbc6de16-ea96-11eb-b4f9-8cc84b59ec7a",
        "anime_url": "https://gum-gum-streaming.com/eyeshield-21-vostfr/",
        "episode_name": "• Épisode 6: Le Spear Tackle fait des ravages",
        "episode_url": "https://gum-gum-streaming.com/eyeshield-21-6-vostfr/"
    },
    {
        "episode_id": "bbca87cb-ea96-11eb-8c75-8cc84b59ec7a",
        "anime_url": "https://gum-gum-streaming.com/eyeshield-21-vostfr/",
        "episode_name": "• Épisode 7: Se battre pour la victoire",
        "episode_url": "https://gum-gum-streaming.com/eyeshield-21-7-vostfr/"
    },
    {
        "episode_id": "bbce5526-ea96-11eb-8dea-8cc84b59ec7a",
        "anime_url": "https://gum-gum-streaming.com/eyeshield-21-vostfr/",
        "episode_name": "• Épisode 8: Je n’abandonnerai pas!",
        "episode_url": "https://gum-gum-streaming.com/eyeshield-21-8-vostfr/"
    },
    {
        "episode_id": "bbd1fede-ea96-11eb-829d-8cc84b59ec7a",
        "anime_url": "https://gum-gum-streaming.com/eyeshield-21-vostfr/",
        "episode_name": "• Épisode 9: Le spécialiste de la réception",
        "episode_url": "https://gum-gum-streaming.com/eyeshield-21-9-vostfr/"
    },
    {
        "episode_id": "bbd71939-ea96-11eb-a71a-8cc84b59ec7a",
        "anime_url": "https://gum-gum-streaming.com/eyeshield-21-vostfr/",
        "episode_name": "• Épisode 10: L’étoffe du héros",
        "episode_url": "https://gum-gum-streaming.com/eyeshield-21-10-vostfr/"
    },
    {
        "episode_id": "bbdaea28-ea96-11eb-907e-8cc84b59ec7a",
        "anime_url": "https://gum-gum-streaming.com/eyeshield-21-vostfr/",
        "episode_name": "• Épisode 11: Le serment du crépuscule",
        "episode_url": "https://gum-gum-streaming.com/eyeshield-21-11-vostfr/"
    },
    {
        "episode_id": "bbdf091a-ea96-11eb-91ab-8cc84b59ec7a",
        "anime_url": "https://gum-gum-streaming.com/eyeshield-21-vostfr/",
        "episode_name": "• Épisode 12: Réception maxi!",
        "episode_url": "https://gum-gum-streaming.com/eyeshield-21-12-vostfr/"
    },
    {
        "episode_id": "bbe2a229-ea96-11eb-92ba-8cc84b59ec7a",
        "anime_url": "https://gum-gum-streaming.com/eyeshield-21-vostfr/",
        "episode_name": "• Épisode 13: Les terribles caméléons",
        "episode_url": "https://gum-gum-streaming.com/eyeshield-21-13-vostfr/"
    },
    {
        "episode_id": "bbe64bdf-ea96-11eb-afc7-8cc84b59ec7a",
        "anime_url": "https://gum-gum-streaming.com/eyeshield-21-vostfr/",
        "episode_name": "• Épisode 14: La tour infernale",
        "episode_url": "https://gum-gum-streaming.com/eyeshield-21-14-vostfr/"
    },
    {
        "episode_id": "bbe9f4ea-ea96-11eb-9b1b-8cc84b59ec7a",
        "anime_url": "https://gum-gum-streaming.com/eyeshield-21-vostfr/",
        "episode_name": "• Épisode 15: Cherchez Eyeshield!",
        "episode_url": "https://gum-gum-streaming.com/eyeshield-21-15-vostfr/"
    },
    {
        "episode_id": "bbedc5a0-ea96-11eb-8a7e-8cc84b59ec7a",
        "anime_url": "https://gum-gum-streaming.com/eyeshield-21-vostfr/",
        "episode_name": "• Épisode 16: Adieu, Kurita!?",
        "episode_url": "https://gum-gum-streaming.com/eyeshield-21-16-vostfr/"
    },
    {
        "episode_id": "bbf19667-ea96-11eb-95c0-8cc84b59ec7a",
        "anime_url": "https://gum-gum-streaming.com/eyeshield-21-vostfr/",
        "episode_name": "• Épisode 17: Kid et le cheval de fer",
        "episode_url": "https://gum-gum-streaming.com/eyeshield-21-17-vostfr/"
    },
    {
        "episode_id": "bbf567f1-ea96-11eb-a5e2-8cc84b59ec7a",
        "anime_url": "https://gum-gum-streaming.com/eyeshield-21-vostfr/",
        "episode_name": "• Épisode 18: La fierté des vauriens",
        "episode_url": "https://gum-gum-streaming.com/eyeshield-21-18-vostfr/"
    },
    {
        "episode_id": "bbf938ce-ea96-11eb-b1b0-8cc84b59ec7a",
        "anime_url": "https://gum-gum-streaming.com/eyeshield-21-vostfr/",
        "episode_name": "• Épisode 19: La bourgeoisie se gausse du challenger",
        "episode_url": "https://gum-gum-streaming.com/eyeshield-21-19-vostfr/"
    },
    {
        "episode_id": "bbfd097b-ea96-11eb-b593-8cc84b59ec7a",
        "anime_url": "https://gum-gum-streaming.com/eyeshield-21-vostfr/",
        "episode_name": "• Épisode 20: L’arme secrète des sphinx",
        "episode_url": "https://gum-gum-streaming.com/eyeshield-21-20-vostfr/"
    },
    {
        "episode_id": "bc00da47-ea96-11eb-bdaa-8cc84b59ec7a",
        "anime_url": "https://gum-gum-streaming.com/eyeshield-21-vostfr/",
        "episode_name": "• Épisode 21: Vole, Devil Bat!",
        "episode_url": "https://gum-gum-streaming.com/eyeshield-21-21-vostfr/"
    },
    {
        "episode_id": "bc048367-ea96-11eb-a0cc-8cc84b59ec7a",
        "anime_url": "https://gum-gum-streaming.com/eyeshield-21-vostfr/",
        "episode_name": "• Épisode 22: L’apparition d’une mystérieuse fille",
        "episode_url": "https://gum-gum-streaming.com/eyeshield-21-22-vostfr/"
    },
    {
        "episode_id": "bc08a325-ea96-11eb-8e3d-8cc84b59ec7a",
        "anime_url": "https://gum-gum-streaming.com/eyeshield-21-vostfr/",
        "episode_name": "• Épisode 23: L’homme qui échappe à la gravité",
        "episode_url": "https://gum-gum-streaming.com/eyeshield-21-23-vostfr/"
    },
    {
        "episode_id": "bc0c6d20-ea96-11eb-9edc-8cc84b59ec7a",
        "anime_url": "https://gum-gum-streaming.com/eyeshield-21-vostfr/",
        "episode_name": "• Épisode 24: La finale Japon/États-Unis éclair",
        "episode_url": "https://gum-gum-streaming.com/eyeshield-21-24-vostfr/"
    },
    {
        "episode_id": "bc101b8a-ea96-11eb-afc0-8cc84b59ec7a",
        "anime_url": "https://gum-gum-streaming.com/eyeshield-21-vostfr/",
        "episode_name": "• Épisode 25: La panthère noire dans sa cage",
        "episode_url": "https://gum-gum-streaming.com/eyeshield-21-25-vostfr/"
    },
    {
        "episode_id": "bc13c547-ea96-11eb-be26-8cc84b59ec7a",
        "anime_url": "https://gum-gum-streaming.com/eyeshield-21-vostfr/",
        "episode_name": "• Épisode 26: Un réel instinct sauvage",
        "episode_url": "https://gum-gum-streaming.com/eyeshield-21-26-vostfr/"
    },
    {
        "episode_id": "bc17aa0a-ea96-11eb-8571-8cc84b59ec7a",
        "anime_url": "https://gum-gum-streaming.com/eyeshield-21-vostfr/",
        "episode_name": "• Épisode 27: Il faut récupérer Cerberos!",
        "episode_url": "https://gum-gum-streaming.com/eyeshield-21-27-vostfr/"
    },
    {
        "episode_id": "bc1b65b1-ea96-11eb-b91f-8cc84b59ec7a",
        "anime_url": "https://gum-gum-streaming.com/eyeshield-21-vostfr/",
        "episode_name": "• Épisode 28: Football américain en ville",
        "episode_url": "https://gum-gum-streaming.com/eyeshield-21-28-vostfr/"
    },
    {
        "episode_id": "bc1f1766-ea96-11eb-83ea-8cc84b59ec7a",
        "anime_url": "https://gum-gum-streaming.com/eyeshield-21-vostfr/",
        "episode_name": "• Épisode 29: Naissance des Devil Gunmen",
        "episode_url": "https://gum-gum-streaming.com/eyeshield-21-29-vostfr/"
    },
    {
        "episode_id": "bc22d48a-ea96-11eb-a636-8cc84b59ec7a",
        "anime_url": "https://gum-gum-streaming.com/eyeshield-21-vostfr/",
        "episode_name": "• Épisode 30: La frontière de l’enfer",
        "episode_url": "https://gum-gum-streaming.com/eyeshield-21-30-vostfr/"
    },
    {
        "episode_id": "bc26cbac-ea96-11eb-91ee-8cc84b59ec7a",
        "anime_url": "https://gum-gum-streaming.com/eyeshield-21-vostfr/",
        "episode_name": "• Épisode 31: La décision de chacun",
        "episode_url": "https://gum-gum-streaming.com/eyeshield-21-31-vostfr/"
    },
    {
        "episode_id": "bc2aa280-ea96-11eb-ad87-8cc84b59ec7a",
        "anime_url": "https://gum-gum-streaming.com/eyeshield-21-vostfr/",
        "episode_name": "• Épisode 32: Y a-t-il des losers?",
        "episode_url": "https://gum-gum-streaming.com/eyeshield-21-32-vostfr/"
    },
    {
        "episode_id": "bc2e6e86-ea96-11eb-80d2-8cc84b59ec7a",
        "anime_url": "https://gum-gum-streaming.com/eyeshield-21-vostfr/",
        "episode_name": "• Épisode 33: Hé! Ma sœur!",
        "episode_url": "https://gum-gum-streaming.com/eyeshield-21-33-vostfr/"
    },
    {
        "episode_id": "bc324426-ea96-11eb-b538-8cc84b59ec7a",
        "anime_url": "https://gum-gum-streaming.com/eyeshield-21-vostfr/",
        "episode_name": "• Épisode 34: Apparition du Ghost",
        "episode_url": "https://gum-gum-streaming.com/eyeshield-21-34-vostfr/"
    },
    {
        "episode_id": "bc365a2f-ea96-11eb-9cf4-8cc84b59ec7a",
        "anime_url": "https://gum-gum-streaming.com/eyeshield-21-vostfr/",
        "episode_name": "• Épisode 35: Solitude dans la marche de la mort",
        "episode_url": "https://gum-gum-streaming.com/eyeshield-21-35-vostfr/"
    },
    {
        "episode_id": "bc3a79aa-ea96-11eb-b4f7-8cc84b59ec7a",
        "anime_url": "https://gum-gum-streaming.com/eyeshield-21-vostfr/",
        "episode_name": "• Épisode 36: La dernière épreuve",
        "episode_url": "https://gum-gum-streaming.com/eyeshield-21-36-vostfr/"
    },
    {
        "episode_id": "bc3e207e-ea96-11eb-9f48-8cc84b59ec7a",
        "anime_url": "https://gum-gum-streaming.com/eyeshield-21-vostfr/",
        "episode_name": "• Épisode 37: Un si haut sommet",
        "episode_url": "https://gum-gum-streaming.com/eyeshield-21-37-vostfr/"
    },
    {
        "episode_id": "bc425434-ea96-11eb-8797-8cc84b59ec7a",
        "anime_url": "https://gum-gum-streaming.com/eyeshield-21-vostfr/",
        "episode_name": "• Épisode 38: Annonce de l’équipe titulaire",
        "episode_url": "https://gum-gum-streaming.com/eyeshield-21-38-vostfr/"
    },
    {
        "episode_id": "bc4672c2-ea96-11eb-af6a-8cc84b59ec7a",
        "anime_url": "https://gum-gum-streaming.com/eyeshield-21-vostfr/",
        "episode_name": "• Épisode 39: En route pour le Christmas Bowl",
        "episode_url": "https://gum-gum-streaming.com/eyeshield-21-39-vostfr/"
    },
    {
        "episode_id": "bc4a6f0b-ea96-11eb-8775-8cc84b59ec7a",
        "anime_url": "https://gum-gum-streaming.com/eyeshield-21-vostfr/",
        "episode_name": "• Épisode 40: La veille du match",
        "episode_url": "https://gum-gum-streaming.com/eyeshield-21-40-vostfr/"
    },
    {
        "episode_id": "bc4e3fcd-ea96-11eb-8ca2-8cc84b59ec7a",
        "anime_url": "https://gum-gum-streaming.com/eyeshield-21-vostfr/",
        "episode_name": "• Épisode 41: Disparition du champion",
        "episode_url": "https://gum-gum-streaming.com/eyeshield-21-41-vostfr/"
    },
    {
        "episode_id": "bc521153-ea96-11eb-8041-8cc84b59ec7a",
        "anime_url": "https://gum-gum-streaming.com/eyeshield-21-vostfr/",
        "episode_name": "• Épisode 42: Le Devil Bat Ghost",
        "episode_url": "https://gum-gum-streaming.com/eyeshield-21-42-vostfr/"
    },
    {
        "episode_id": "bc562c14-ea96-11eb-837b-8cc84b59ec7a",
        "anime_url": "https://gum-gum-streaming.com/eyeshield-21-vostfr/",
        "episode_name": "• Épisode 43: Le légendaire Magnum de 60 yards",
        "episode_url": "https://gum-gum-streaming.com/eyeshield-21-43-vostfr/"
    },
    {
        "episode_id": "bc5a1c75-ea96-11eb-aea2-8cc84b59ec7a",
        "anime_url": "https://gum-gum-streaming.com/eyeshield-21-vostfr/",
        "episode_name": "• Épisode 44: Ahaha! Je fais mes débuts!",
        "episode_url": "https://gum-gum-streaming.com/eyeshield-21-44-vostfr/"
    },
    {
        "episode_id": "bc5dc5a3-ea96-11eb-a6f8-8cc84b59ec7a",
        "anime_url": "https://gum-gum-streaming.com/eyeshield-21-vostfr/",
        "episode_name": "• Épisode 45: Le Ghost est interdit",
        "episode_url": "https://gum-gum-streaming.com/eyeshield-21-45-vostfr/"
    },
    {
        "episode_id": "bc61a47c-ea96-11eb-951f-8cc84b59ec7a",
        "anime_url": "https://gum-gum-streaming.com/eyeshield-21-vostfr/",
        "episode_name": "• Épisode 46: Ghost contre Spear",
        "episode_url": "https://gum-gum-streaming.com/eyeshield-21-46-vostfr/"
    },
    {
        "episode_id": "bc660793-ea96-11eb-94ba-8cc84b59ec7a",
        "anime_url": "https://gum-gum-streaming.com/eyeshield-21-vostfr/",
        "episode_name": "• Épisode 47: Ils sont chauds, les Guts!",
        "episode_url": "https://gum-gum-streaming.com/eyeshield-21-47-vostfr/"
    },
    {
        "episode_id": "bc69d79d-ea96-11eb-9acb-8cc84b59ec7a",
        "anime_url": "https://gum-gum-streaming.com/eyeshield-21-vostfr/",
        "episode_name": "• Épisode 48: Effort, cran, et match à pleine puissance!",
        "episode_url": "https://gum-gum-streaming.com/eyeshield-21-48-vostfr/"
    },
    {
        "episode_id": "bc6d8f50-ea96-11eb-8324-8cc84b59ec7a",
        "anime_url": "https://gum-gum-streaming.com/eyeshield-21-vostfr/",
        "episode_name": "• Épisode 49: L’esprit d’honneur de la ligne",
        "episode_url": "https://gum-gum-streaming.com/eyeshield-21-49-vostfr/"
    },
    {
        "episode_id": "bc71fcec-ea96-11eb-89c4-8cc84b59ec7a",
        "anime_url": "https://gum-gum-streaming.com/eyeshield-21-vostfr/",
        "episode_name": "• Épisode 50: Le courage de ne pas fuir!",
        "episode_url": "https://gum-gum-streaming.com/eyeshield-21-50-vostfr/"
    },
    {
        "episode_id": "bc75cdb5-ea96-11eb-a927-8cc84b59ec7a",
        "anime_url": "https://gum-gum-streaming.com/eyeshield-21-vostfr/",
        "episode_name": "• Épisode 51: Les violents Caméléons sont en danger",
        "episode_url": "https://gum-gum-streaming.com/eyeshield-21-51-vostfr/"
    },
    {
        "episode_id": "bc7a12fd-ea96-11eb-841f-8cc84b59ec7a",
        "anime_url": "https://gum-gum-streaming.com/eyeshield-21-vostfr/",
        "episode_name": "• Épisode 52: Le choc! Les Caméléons contre les Poséidon!",
        "episode_url": "https://gum-gum-streaming.com/eyeshield-21-52-vostfr/"
    },
    {
        "episode_id": "bc8278a4-ea96-11eb-949e-8cc84b59ec7a",
        "anime_url": "https://gum-gum-streaming.com/eyeshield-21-vostfr/",
        "episode_name": "• Épisode 53: Le terrifiant Scorpion venimeux",
        "episode_url": "https://gum-gum-streaming.com/eyeshield-21-53-vostfr/"
    },
    {
        "episode_id": "bc862272-ea96-11eb-9e0f-8cc84b59ec7a",
        "anime_url": "https://gum-gum-streaming.com/eyeshield-21-vostfr/",
        "episode_name": "• Épisode 54: La tour de contrôle a disparu",
        "episode_url": "https://gum-gum-streaming.com/eyeshield-21-54-vostfr/"
    },
    {
        "episode_id": "bc89f33b-ea96-11eb-ac74-8cc84b59ec7a",
        "anime_url": "https://gum-gum-streaming.com/eyeshield-21-vostfr/",
        "episode_name": "• Épisode 55: Le mur de la différence de taille",
        "episode_url": "https://gum-gum-streaming.com/eyeshield-21-55-vostfr/"
    },
    {
        "episode_id": "bc8dc3e5-ea96-11eb-bb1e-8cc84b59ec7a",
        "anime_url": "https://gum-gum-streaming.com/eyeshield-21-vostfr/",
        "episode_name": "• Épisode 56: Pousse, Komusubizeki!",
        "episode_url": "https://gum-gum-streaming.com/eyeshield-21-56-vostfr/"
    },
    {
        "episode_id": "bc91941d-ea96-11eb-87ed-8cc84b59ec7a",
        "anime_url": "https://gum-gum-streaming.com/eyeshield-21-vostfr/",
        "episode_name": "• Épisode 57: Celui qui connaît le numéro 21",
        "episode_url": "https://gum-gum-streaming.com/eyeshield-21-57-vostfr/"
    },
    {
        "episode_id": "bc95d9f4-ea96-11eb-9eac-8cc84b59ec7a",
        "anime_url": "https://gum-gum-streaming.com/eyeshield-21-vostfr/",
        "episode_name": "• Épisode 58: Le démon contre le dieu de la mer",
        "episode_url": "https://gum-gum-streaming.com/eyeshield-21-58-vostfr/"
    },
    {
        "episode_id": "bc99f118-ea96-11eb-a84b-8cc84b59ec7a",
        "anime_url": "https://gum-gum-streaming.com/eyeshield-21-vostfr/",
        "episode_name": "• Épisode 59: La vedette cachée",
        "episode_url": "https://gum-gum-streaming.com/eyeshield-21-59-vostfr/"
    },
    {
        "episode_id": "bc9dd6a8-ea96-11eb-b55b-8cc84b59ec7a",
        "anime_url": "https://gum-gum-streaming.com/eyeshield-21-vostfr/",
        "episode_name": "• Épisode 60: La promesse du terrain",
        "episode_url": "https://gum-gum-streaming.com/eyeshield-21-60-vostfr/"
    },
    {
        "episode_id": "bca1a772-ea96-11eb-a915-8cc84b59ec7a",
        "anime_url": "https://gum-gum-streaming.com/eyeshield-21-vostfr/",
        "episode_name": "• Épisode 61: L’obsession de la victoire",
        "episode_url": "https://gum-gum-streaming.com/eyeshield-21-61-vostfr/"
    },
    {
        "episode_id": "bca6866b-ea96-11eb-812d-8cc84b59ec7a",
        "anime_url": "https://gum-gum-streaming.com/eyeshield-21-vostfr/",
        "episode_name": "• Épisode 62: L’effroyable Moby Dick Anchor!",
        "episode_url": "https://gum-gum-streaming.com/eyeshield-21-62-vostfr/"
    },
    {
        "episode_id": "bcaa4ec9-ea96-11eb-b87a-8cc84b59ec7a",
        "anime_url": "https://gum-gum-streaming.com/eyeshield-21-vostfr/",
        "episode_name": "• Épisode 63: Offensive et défensive sur 30 centimètres",
        "episode_url": "https://gum-gum-streaming.com/eyeshield-21-63-vostfr/"
    },
    {
        "episode_id": "bcae94ba-ea96-11eb-9271-8cc84b59ec7a",
        "anime_url": "https://gum-gum-streaming.com/eyeshield-21-vostfr/",
        "episode_name": "• Épisode 64: L’apparition d’un homme rapide comme la lumière",
        "episode_url": "https://gum-gum-streaming.com/eyeshield-21-64-vostfr/"
    },
    {
        "episode_id": "bcb26584-ea96-11eb-90b7-8cc84b59ec7a",
        "anime_url": "https://gum-gum-streaming.com/eyeshield-21-vostfr/",
        "episode_name": "• Épisode 65: C’est la fête du sport au lycée Deimon!",
        "episode_url": "https://gum-gum-streaming.com/eyeshield-21-65-vostfr/"
    },
    {
        "episode_id": "bcb6365f-ea96-11eb-9b78-8cc84b59ec7a",
        "anime_url": "https://gum-gum-streaming.com/eyeshield-21-vostfr/",
        "episode_name": "• Épisode 66: Sena, sprinter?",
        "episode_url": "https://gum-gum-streaming.com/eyeshield-21-66-vostfr/"
    },
    {
        "episode_id": "bcba07e9-ea96-11eb-8dab-8cc84b59ec7a",
        "anime_url": "https://gum-gum-streaming.com/eyeshield-21-vostfr/",
        "episode_name": "• Épisode 67: La promesse des trois amis",
        "episode_url": "https://gum-gum-streaming.com/eyeshield-21-67-vostfr/"
    },
    {
        "episode_id": "bcbdffc8-ea96-11eb-85bf-8cc84b59ec7a",
        "anime_url": "https://gum-gum-streaming.com/eyeshield-21-vostfr/",
        "episode_name": "• Épisode 68: Prouver qui est le plus rapide",
        "episode_url": "https://gum-gum-streaming.com/eyeshield-21-68-vostfr/"
    },
    {
        "episode_id": "bcc245c6-ea96-11eb-895f-8cc84b59ec7a",
        "anime_url": "https://gum-gum-streaming.com/eyeshield-21-vostfr/",
        "episode_name": "• Épisode 69: Désespoir sur le terrain",
        "episode_url": "https://gum-gum-streaming.com/eyeshield-21-69-vostfr/"
    },
    {
        "episode_id": "bcc5ef7b-ea96-11eb-aaf4-8cc84b59ec7a",
        "anime_url": "https://gum-gum-streaming.com/eyeshield-21-vostfr/",
        "episode_name": "• Épisode 70: Musashi est avec nous",
        "episode_url": "https://gum-gum-streaming.com/eyeshield-21-70-vostfr/"
    },
    {
        "episode_id": "bcca3080-ea96-11eb-8064-8cc84b59ec7a",
        "anime_url": "https://gum-gum-streaming.com/eyeshield-21-vostfr/",
        "episode_name": "• Épisode 71: Le démon de la contre-attaque",
        "episode_url": "https://gum-gum-streaming.com/eyeshield-21-71-vostfr/"
    },
    {
        "episode_id": "bcce0e47-ea96-11eb-9df0-8cc84b59ec7a",
        "anime_url": "https://gum-gum-streaming.com/eyeshield-21-vostfr/",
        "episode_name": "• Épisode 72: Fierté et vitesse de la lumière",
        "episode_url": "https://gum-gum-streaming.com/eyeshield-21-72-vostfr/"
    },
    {
        "episode_id": "bcd208c6-ea96-11eb-9e32-8cc84b59ec7a",
        "anime_url": "https://gum-gum-streaming.com/eyeshield-21-vostfr/",
        "episode_name": "• Épisode 73: Le tir du destin",
        "episode_url": "https://gum-gum-streaming.com/eyeshield-21-73-vostfr/"
    },
    {
        "episode_id": "bcd5d984-ea96-11eb-8b5d-8cc84b59ec7a",
        "anime_url": "https://gum-gum-streaming.com/eyeshield-21-vostfr/",
        "episode_name": "• Épisode 74: Le serment des rivaux",
        "episode_url": "https://gum-gum-streaming.com/eyeshield-21-74-vostfr/"
    },
    {
        "episode_id": "bcdc90d7-ea96-11eb-bb07-8cc84b59ec7a",
        "anime_url": "https://gum-gum-streaming.com/eyeshield-21-vostfr/",
        "episode_name": "• Épisode 75: La menace de Bando",
        "episode_url": "https://gum-gum-streaming.com/eyeshield-21-75-vostfr/"
    },
    {
        "episode_id": "bce08937-ea96-11eb-bab3-8cc84b59ec7a",
        "anime_url": "https://gum-gum-streaming.com/eyeshield-21-vostfr/",
        "episode_name": "• Épisode 76: Reviens! Musashi!",
        "episode_url": "https://gum-gum-streaming.com/eyeshield-21-76-vostfr/"
    },
    {
        "episode_id": "bce45075-ea96-11eb-ae84-8cc84b59ec7a",
        "anime_url": "https://gum-gum-streaming.com/eyeshield-21-vostfr/",
        "episode_name": "• Épisode 77: Le véritable numéro 21",
        "episode_url": "https://gum-gum-streaming.com/eyeshield-21-77-vostfr/"
    },
    {
        "episode_id": "bce7a8b4-ea96-11eb-9251-8cc84b59ec7a",
        "anime_url": "https://gum-gum-streaming.com/eyeshield-21-vostfr/",
        "episode_name": "• Épisode 78: Ceux qui attendent au bout du chemin",
        "episode_url": "https://gum-gum-streaming.com/eyeshield-21-78-vostfr/"
    },
    {
        "episode_id": "bceb7a0a-ea96-11eb-b891-8cc84b59ec7a",
        "anime_url": "https://gum-gum-streaming.com/eyeshield-21-vostfr/",
        "episode_name": "• Épisode 79: Sena Kobayakawa",
        "episode_url": "https://gum-gum-streaming.com/eyeshield-21-79-vostfr/"
    },
    {
        "episode_id": "bcef71e8-ea96-11eb-831a-8cc84b59ec7a",
        "anime_url": "https://gum-gum-streaming.com/eyeshield-21-vostfr/",
        "episode_name": "• Épisode 80: La meilleure équipe de tireurs",
        "episode_url": "https://gum-gum-streaming.com/eyeshield-21-80-vostfr/"
    },
    {
        "episode_id": "bcf31b4c-ea96-11eb-89a3-8cc84b59ec7a",
        "anime_url": "https://gum-gum-streaming.com/eyeshield-21-vostfr/",
        "episode_name": "• Épisode 81: La vérité sur l’homme aux yeux rouges",
        "episode_url": "https://gum-gum-streaming.com/eyeshield-21-81-vostfr/"
    },
    {
        "episode_id": "bcf67bdc-ea96-11eb-911f-8cc84b59ec7a",
        "anime_url": "https://gum-gum-streaming.com/eyeshield-21-vostfr/",
        "episode_name": "• Épisode 82: Cours, Musashi!",
        "episode_url": "https://gum-gum-streaming.com/eyeshield-21-82-vostfr/"
    },
    {
        "episode_id": "bcf9adf8-ea96-11eb-a9c9-8cc84b59ec7a",
        "anime_url": "https://gum-gum-streaming.com/eyeshield-21-vostfr/",
        "episode_name": "• Épisode 83: Le temps a repris son cours",
        "episode_url": "https://gum-gum-streaming.com/eyeshield-21-83-vostfr/"
    },
    {
        "episode_id": "bcfbd60b-ea96-11eb-883b-8cc84b59ec7a",
        "anime_url": "https://gum-gum-streaming.com/eyeshield-21-vostfr/",
        "episode_name": "• Épisode 84: Le Démon dans la tempête",
        "episode_url": "https://gum-gum-streaming.com/eyeshield-21-84-vostfr/"
    },
    {
        "episode_id": "bcfe2568-ea96-11eb-8a33-8cc84b59ec7a",
        "anime_url": "https://gum-gum-streaming.com/eyeshield-21-vostfr/",
        "episode_name": "• Épisode 85: L’homme aimé de Dieu",
        "episode_url": "https://gum-gum-streaming.com/eyeshield-21-85-vostfr/"
    },
    {
        "episode_id": "bd00955e-ea96-11eb-800b-8cc84b59ec7a",
        "anime_url": "https://gum-gum-streaming.com/eyeshield-21-vostfr/",
        "episode_name": "• Épisode 86: Ombre et lumière d’une fin de match",
        "episode_url": "https://gum-gum-streaming.com/eyeshield-21-86-vostfr/"
    },
    {
        "episode_id": "bd02e4e0-ea96-11eb-a240-8cc84b59ec7a",
        "anime_url": "https://gum-gum-streaming.com/eyeshield-21-vostfr/",
        "episode_name": "• Épisode 87: Les guerriers les plus forts de Tokyo",
        "episode_url": "https://gum-gum-streaming.com/eyeshield-21-87-vostfr/"
    },
    {
        "episode_id": "bd057cd1-ea96-11eb-99bb-8cc84b59ec7a",
        "anime_url": "https://gum-gum-streaming.com/eyeshield-21-vostfr/",
        "episode_name": "• Épisode 88: Show de mi-temps à Deimon",
        "episode_url": "https://gum-gum-streaming.com/eyeshield-21-88-vostfr/"
    },
    {
        "episode_id": "bd083c1c-ea96-11eb-abdd-8cc84b59ec7a",
        "anime_url": "https://gum-gum-streaming.com/eyeshield-21-vostfr/",
        "episode_name": "• Épisode 89: Ouverture de la coupe choux à la crème",
        "episode_url": "https://gum-gum-streaming.com/eyeshield-21-89-vostfr/"
    },
    {
        "episode_id": "bd0bbebf-ea96-11eb-8f37-8cc84b59ec7a",
        "anime_url": "https://gum-gum-streaming.com/eyeshield-21-vostfr/",
        "episode_name": "• Épisode 90: Une nouvelle épreuve",
        "episode_url": "https://gum-gum-streaming.com/eyeshield-21-90-vostfr/"
    },
    {
        "episode_id": "bd0f1a54-ea96-11eb-9791-8cc84b59ec7a",
        "anime_url": "https://gum-gum-streaming.com/eyeshield-21-vostfr/",
        "episode_name": "• Épisode 91: L’esprit combattif! L’ascension de la mort",
        "episode_url": "https://gum-gum-streaming.com/eyeshield-21-91-vostfr/"
    },
    {
        "episode_id": "bd124ed7-ea96-11eb-af81-8cc84b59ec7a",
        "anime_url": "https://gum-gum-streaming.com/eyeshield-21-vostfr/",
        "episode_name": "• Épisode 92: Les trois frères dans un ranch du Texas",
        "episode_url": "https://gum-gum-streaming.com/eyeshield-21-92-vostfr/"
    },
    {
        "episode_id": "bd15789b-ea96-11eb-8b70-8cc84b59ec7a",
        "anime_url": "https://gum-gum-streaming.com/eyeshield-21-vostfr/",
        "episode_name": "• Épisode 93: Encouragements amicaux",
        "episode_url": "https://gum-gum-streaming.com/eyeshield-21-93-vostfr/"
    },
    {
        "episode_id": "bd1900f2-ea96-11eb-a6aa-8cc84b59ec7a",
        "anime_url": "https://gum-gum-streaming.com/eyeshield-21-vostfr/",
        "episode_name": "• Épisode 94: L’arme secrète couleur argent",
        "episode_url": "https://gum-gum-streaming.com/eyeshield-21-94-vostfr/"
    },
    {
        "episode_id": "bd1cbf53-ea96-11eb-a5eb-8cc84b59ec7a",
        "anime_url": "https://gum-gum-streaming.com/eyeshield-21-vostfr/",
        "episode_name": "• Épisode 95: Brisez le mur de la tempête de neige!",
        "episode_url": "https://gum-gum-streaming.com/eyeshield-21-95-vostfr/"
    },
    {
        "episode_id": "bd202e5c-ea96-11eb-8ba7-8cc84b59ec7a",
        "anime_url": "https://gum-gum-streaming.com/eyeshield-21-vostfr/",
        "episode_name": "• Épisode 96: Allez! Sus au tournoi du Kanto!",
        "episode_url": "https://gum-gum-streaming.com/eyeshield-21-96-vostfr/"
    },
    {
        "episode_id": "bd23a5dc-ea96-11eb-9d31-8cc84b59ec7a",
        "anime_url": "https://gum-gum-streaming.com/eyeshield-21-vostfr/",
        "episode_name": "• Épisode 97: Adieu, Onihei!",
        "episode_url": "https://gum-gum-streaming.com/eyeshield-21-97-vostfr/"
    },
    {
        "episode_id": "bd272fd7-ea96-11eb-9cdf-8cc84b59ec7a",
        "anime_url": "https://gum-gum-streaming.com/eyeshield-21-vostfr/",
        "episode_name": "• Épisode 98: La riposte des Caméléons",
        "episode_url": "https://gum-gum-streaming.com/eyeshield-21-98-vostfr/"
    },
    {
        "episode_id": "bd2a951f-ea96-11eb-b276-8cc84b59ec7a",
        "anime_url": "https://gum-gum-streaming.com/eyeshield-21-vostfr/",
        "episode_name": "• Épisode 99: C’est la fête de l’école au lycée Deimon",
        "episode_url": "https://gum-gum-streaming.com/eyeshield-21-99-vostfr/"
    },
    {
        "episode_id": "bd2e3092-ea96-11eb-95fd-8cc84b59ec7a",
        "anime_url": "https://gum-gum-streaming.com/eyeshield-21-vostfr/",
        "episode_name": "• Épisode 100: Des chaînes invisibles",
        "episode_url": "https://gum-gum-streaming.com/eyeshield-21-100-vostfr/"
    },
    {
        "episode_id": "bd3195ba-ea96-11eb-8599-8cc84b59ec7a",
        "anime_url": "https://gum-gum-streaming.com/eyeshield-21-vostfr/",
        "episode_name": "• Épisode 101: Le plus puissant des démons",
        "episode_url": "https://gum-gum-streaming.com/eyeshield-21-101-vostfr/"
    },
    {
        "episode_id": "bd35568b-ea96-11eb-a133-8cc84b59ec7a",
        "anime_url": "https://gum-gum-streaming.com/eyeshield-21-vostfr/",
        "episode_name": "• Épisode 102: Surmonter sa peur",
        "episode_url": "https://gum-gum-streaming.com/eyeshield-21-102-vostfr/"
    },
    {
        "episode_id": "bd392773-ea96-11eb-83a8-8cc84b59ec7a",
        "anime_url": "https://gum-gum-streaming.com/eyeshield-21-vostfr/",
        "episode_name": "• Épisode 103: Un double blocage infranchissable",
        "episode_url": "https://gum-gum-streaming.com/eyeshield-21-103-vostfr/"
    },
    {
        "episode_id": "bd3c8415-ea96-11eb-9723-8cc84b59ec7a",
        "anime_url": "https://gum-gum-streaming.com/eyeshield-21-vostfr/",
        "episode_name": "• Épisode 104: Le joueur de ligne manquant",
        "episode_url": "https://gum-gum-streaming.com/eyeshield-21-104-vostfr/"
    },
    {
        "episode_id": "bd41f9fb-ea96-11eb-bae5-8cc84b59ec7a",
        "anime_url": "https://gum-gum-streaming.com/eyeshield-21-vostfr/",
        "episode_name": "• Épisode 105: L’ultime match du jeu de la mort",
        "episode_url": "https://gum-gum-streaming.com/eyeshield-21-105-vostfr/"
    },
    {
        "episode_id": "bd443dc2-ea96-11eb-b3be-8cc84b59ec7a",
        "anime_url": "https://gum-gum-streaming.com/eyeshield-21-vostfr/",
        "episode_name": "• Épisode 106: Agon Kongo, le dieu-démon",
        "episode_url": "https://gum-gum-streaming.com/eyeshield-21-106-vostfr/"
    },
    {
        "episode_id": "bd4663e3-ea96-11eb-b653-8cc84b59ec7a",
        "anime_url": "https://gum-gum-streaming.com/eyeshield-21-vostfr/",
        "episode_name": "• Épisode 107: L’ennemi est à Shinryuji!",
        "episode_url": "https://gum-gum-streaming.com/eyeshield-21-107-vostfr/"
    },
    {
        "episode_id": "bd48861f-ea96-11eb-bdb3-8cc84b59ec7a",
        "anime_url": "https://gum-gum-streaming.com/eyeshield-21-vostfr/",
        "episode_name": "• Épisode 108: Sena, détective?",
        "episode_url": "https://gum-gum-streaming.com/eyeshield-21-108-vostfr/"
    },
    {
        "episode_id": "bd4ae23d-ea96-11eb-aa78-8cc84b59ec7a",
        "anime_url": "https://gum-gum-streaming.com/eyeshield-21-vostfr/",
        "episode_name": "• Épisode 109: Le talent de la réception",
        "episode_url": "https://gum-gum-streaming.com/eyeshield-21-109-vostfr/"
    },
    {
        "episode_id": "bd4d0368-ea96-11eb-8864-8cc84b59ec7a",
        "anime_url": "https://gum-gum-streaming.com/eyeshield-21-vostfr/",
        "episode_name": "• Épisode 110: Le mur du talent",
        "episode_url": "https://gum-gum-streaming.com/eyeshield-21-110-vostfr/"
    },
    {
        "episode_id": "bd4f5b27-ea96-11eb-8bb4-8cc84b59ec7a",
        "anime_url": "https://gum-gum-streaming.com/eyeshield-21-vostfr/",
        "episode_name": "• Épisode 111: Sus à l’ennemi, Devil Bats!",
        "episode_url": "https://gum-gum-streaming.com/eyeshield-21-111-vostfr/"
    },
    {
        "episode_id": "bd519aae-ea96-11eb-9fbe-8cc84b59ec7a",
        "anime_url": "https://gum-gum-streaming.com/eyeshield-21-vostfr/",
        "episode_name": "• Épisode 112: Démon contre Dieu du mal!",
        "episode_url": "https://gum-gum-streaming.com/eyeshield-21-112-vostfr/"
    },
    {
        "episode_id": "bd53c7c1-ea96-11eb-843e-8cc84b59ec7a",
        "anime_url": "https://gum-gum-streaming.com/eyeshield-21-vostfr/",
        "episode_name": "• Épisode 113: Le douzième athlète",
        "episode_url": "https://gum-gum-streaming.com/eyeshield-21-113-vostfr/"
    },
    {
        "episode_id": "bd5613d1-ea96-11eb-9d8e-8cc84b59ec7a",
        "anime_url": "https://gum-gum-streaming.com/eyeshield-21-vostfr/",
        "episode_name": "• Épisode 114: Le potentiel des joueurs ordinaires",
        "episode_url": "https://gum-gum-streaming.com/eyeshield-21-114-vostfr/"
    },
    {
        "episode_id": "bd583acb-ea96-11eb-9186-8cc84b59ec7a",
        "anime_url": "https://gum-gum-streaming.com/eyeshield-21-vostfr/",
        "episode_name": "• Épisode 115: Duel pour le titre de numéro un",
        "episode_url": "https://gum-gum-streaming.com/eyeshield-21-115-vostfr/"
    },
    {
        "episode_id": "bd5a8bfd-ea96-11eb-8d97-8cc84b59ec7a",
        "anime_url": "https://gum-gum-streaming.com/eyeshield-21-vostfr/",
        "episode_name": "• Épisode 116: La volonté du combattant",
        "episode_url": "https://gum-gum-streaming.com/eyeshield-21-116-vostfr/"
    },
    {
        "episode_id": "bd5cae4f-ea96-11eb-9d1f-8cc84b59ec7a",
        "anime_url": "https://gum-gum-streaming.com/eyeshield-21-vostfr/",
        "episode_name": "• Épisode 117: Plus de temps mort",
        "episode_url": "https://gum-gum-streaming.com/eyeshield-21-117-vostfr/"
    },
    {
        "episode_id": "bd5edc33-ea96-11eb-bb98-8cc84b59ec7a",
        "anime_url": "https://gum-gum-streaming.com/eyeshield-21-vostfr/",
        "episode_name": "• Épisode 118: Un huddle sans réponse",
        "episode_url": "https://gum-gum-streaming.com/eyeshield-21-118-vostfr/"
    },
    {
        "episode_id": "bd611dbc-ea96-11eb-b287-8cc84b59ec7a",
        "anime_url": "https://gum-gum-streaming.com/eyeshield-21-vostfr/",
        "episode_name": "• Épisode 119: Au bout d’une lutte acharnée",
        "episode_url": "https://gum-gum-streaming.com/eyeshield-21-119-vostfr/"
    },
    {
        "episode_id": "bd63848a-ea96-11eb-a2bf-8cc84b59ec7a",
        "anime_url": "https://gum-gum-streaming.com/eyeshield-21-vostfr/",
        "episode_name": "• Épisode 120: L’incroyable phénomène Dinosaurs!",
        "episode_url": "https://gum-gum-streaming.com/eyeshield-21-120-vostfr/"
    },
    {
        "episode_id": "bd6643b2-ea96-11eb-8d57-8cc84b59ec7a",
        "anime_url": "https://gum-gum-streaming.com/eyeshield-21-vostfr/",
        "episode_name": "• Épisode 121: Le champ de bataille du loup",
        "episode_url": "https://gum-gum-streaming.com/eyeshield-21-121-vostfr/"
    },
    {
        "episode_id": "bd68dbfa-ea96-11eb-97e4-8cc84b59ec7a",
        "anime_url": "https://gum-gum-streaming.com/eyeshield-21-vostfr/",
        "episode_name": "• Épisode 122: Le Rodeo Drive Stampede",
        "episode_url": "https://gum-gum-streaming.com/eyeshield-21-122-vostfr/"
    },
    {
        "episode_id": "bd6bccf9-ea96-11eb-ac96-8cc84b59ec7a",
        "anime_url": "https://gum-gum-streaming.com/eyeshield-21-vostfr/",
        "episode_name": "• Épisode 123: Un chevalier sans faille",
        "episode_url": "https://gum-gum-streaming.com/eyeshield-21-123-vostfr/"
    },
    {
        "episode_id": "bd70f4a9-ea96-11eb-be9a-8cc84b59ec7a",
        "anime_url": "https://gum-gum-streaming.com/eyeshield-21-vostfr/",
        "episode_name": "• Épisode 124: La lance ultime!",
        "episode_url": "https://gum-gum-streaming.com/eyeshield-21-124-vostfr/"
    },
    {
        "episode_id": "bd7501b7-ea96-11eb-9027-8cc84b59ec7a",
        "anime_url": "https://gum-gum-streaming.com/eyeshield-21-vostfr/",
        "episode_name": "• Épisode 125: C’est la fête de l’école au lycée Ojô!",
        "episode_url": "https://gum-gum-streaming.com/eyeshield-21-125-vostfr/"
    },
    {
        "episode_id": "bd78b0e9-ea96-11eb-a43d-8cc84b59ec7a",
        "anime_url": "https://gum-gum-streaming.com/eyeshield-21-vostfr/",
        "episode_name": "• Épisode 126: L’engagement de devenir un as",
        "episode_url": "https://gum-gum-streaming.com/eyeshield-21-126-vostfr/"
    },
    {
        "episode_id": "bd7c60ad-ea96-11eb-bc71-8cc84b59ec7a",
        "anime_url": "https://gum-gum-streaming.com/eyeshield-21-vostfr/",
        "episode_name": "• Épisode 127: Juste pour la victoire",
        "episode_url": "https://gum-gum-streaming.com/eyeshield-21-127-vostfr/"
    },
    {
        "episode_id": "bd7fff8f-ea96-11eb-9e0a-8cc84b59ec7a",
        "anime_url": "https://gum-gum-streaming.com/eyeshield-21-vostfr/",
        "episode_name": "• Épisode 128: Le démon contre l’homme à la vitesse de la lumière",
        "episode_url": "https://gum-gum-streaming.com/eyeshield-21-128-vostfr/"
    },
    {
        "episode_id": "bd83883a-ea96-11eb-a7a8-8cc84b59ec7a",
        "anime_url": "https://gum-gum-streaming.com/eyeshield-21-vostfr/",
        "episode_name": "• Épisode 129: Le défi au Roi",
        "episode_url": "https://gum-gum-streaming.com/eyeshield-21-129-vostfr/"
    },
    {
        "episode_id": "bd8731bb-ea96-11eb-8646-8cc84b59ec7a",
        "anime_url": "https://gum-gum-streaming.com/eyeshield-21-vostfr/",
        "episode_name": "• Épisode 130: Début des hostilités en fanfare",
        "episode_url": "https://gum-gum-streaming.com/eyeshield-21-130-vostfr/"
    },
    {
        "episode_id": "bd89b986-ea96-11eb-8389-8cc84b59ec7a",
        "anime_url": "https://gum-gum-streaming.com/eyeshield-21-vostfr/",
        "episode_name": "• Épisode 131: Prison Chain, l’enragé",
        "episode_url": "https://gum-gum-streaming.com/eyeshield-21-131-vostfr/"
    },
    {
        "episode_id": "bd8c287d-ea96-11eb-b9c5-8cc84b59ec7a",
        "anime_url": "https://gum-gum-streaming.com/eyeshield-21-vostfr/",
        "episode_name": "• Épisode 132: Le chevalier maître des airs",
        "episode_url": "https://gum-gum-streaming.com/eyeshield-21-132-vostfr/"
    },
    {
        "episode_id": "bd8ef333-ea96-11eb-a6b8-8cc84b59ec7a",
        "anime_url": "https://gum-gum-streaming.com/eyeshield-21-vostfr/",
        "episode_name": "• Épisode 133: La baliste du royaume",
        "episode_url": "https://gum-gum-streaming.com/eyeshield-21-133-vostfr/"
    },
    {
        "episode_id": "bd91871f-ea96-11eb-ad81-8cc84b59ec7a",
        "anime_url": "https://gum-gum-streaming.com/eyeshield-21-vostfr/",
        "episode_name": "• Épisode 134: Un rempart invincible",
        "episode_url": "https://gum-gum-streaming.com/eyeshield-21-134-vostfr/"
    },
    {
        "episode_id": "bd943e15-ea96-11eb-97f0-8cc84b59ec7a",
        "anime_url": "https://gum-gum-streaming.com/eyeshield-21-vostfr/",
        "episode_name": "• Épisode 135: Un surhomme sans égal",
        "episode_url": "https://gum-gum-streaming.com/eyeshield-21-135-vostfr/"
    },
    {
        "episode_id": "bd96d675-ea96-11eb-8dda-8cc84b59ec7a",
        "anime_url": "https://gum-gum-streaming.com/eyeshield-21-vostfr/",
        "episode_name": "• Épisode 136: La défaite du n°21",
        "episode_url": "https://gum-gum-streaming.com/eyeshield-21-136-vostfr/"
    },
    {
        "episode_id": "bd996c4c-ea96-11eb-ad27-8cc84b59ec7a",
        "anime_url": "https://gum-gum-streaming.com/eyeshield-21-vostfr/",
        "episode_name": "• Épisode 137: La mi-temps fatidique",
        "episode_url": "https://gum-gum-streaming.com/eyeshield-21-137-vostfr/"
    },
    {
        "episode_id": "bd9c2c6d-ea96-11eb-939b-8cc84b59ec7a",
        "anime_url": "https://gum-gum-streaming.com/eyeshield-21-vostfr/",
        "episode_name": "• Épisode 138: Bataille sur le terrain après la pluie",
        "episode_url": "https://gum-gum-streaming.com/eyeshield-21-138-vostfr/"
    },
    {
        "episode_id": "bd9f1079-ea96-11eb-a02d-8cc84b59ec7a",
        "anime_url": "https://gum-gum-streaming.com/eyeshield-21-vostfr/",
        "episode_name": "• Épisode 139: Les 9999 réceptions",
        "episode_url": "https://gum-gum-streaming.com/eyeshield-21-139-vostfr/"
    },
    {
        "episode_id": "bda32f62-ea96-11eb-a4fb-8cc84b59ec7a",
        "anime_url": "https://gum-gum-streaming.com/eyeshield-21-vostfr/",
        "episode_name": "• Épisode 140: Les 2 As",
        "episode_url": "https://gum-gum-streaming.com/eyeshield-21-140-vostfr/"
    },
    {
        "episode_id": "bda68af2-ea96-11eb-82af-8cc84b59ec7a",
        "anime_url": "https://gum-gum-streaming.com/eyeshield-21-vostfr/",
        "episode_name": "• Épisode 141: Activation du Devil Stun Gun!",
        "episode_url": "https://gum-gum-streaming.com/eyeshield-21-141-vostfr/"
    },
    {
        "episode_id": "bdaa34d5-ea96-11eb-b0ca-8cc84b59ec7a",
        "anime_url": "https://gum-gum-streaming.com/eyeshield-21-vostfr/",
        "episode_name": "• Épisode 142: Les deux ailes du Démon",
        "episode_url": "https://gum-gum-streaming.com/eyeshield-21-142-vostfr/"
    },
    {
        "episode_id": "bdad80c9-ea96-11eb-8006-8cc84b59ec7a",
        "anime_url": "https://gum-gum-streaming.com/eyeshield-21-vostfr/",
        "episode_name": "• Épisode 143: Par pure volonté",
        "episode_url": "https://gum-gum-streaming.com/eyeshield-21-143-vostfr/"
    },
    {
        "episode_id": "bdb10237-ea96-11eb-8918-8cc84b59ec7a",
        "anime_url": "https://gum-gum-streaming.com/eyeshield-21-vostfr/",
        "episode_name": "• Épisode 144: L’instant ultime",
        "episode_url": "https://gum-gum-streaming.com/eyeshield-21-144-vostfr/"
    },
    {
        "episode_id": "bdb4cf1c-ea96-11eb-a4bd-8cc84b59ec7a",
        "anime_url": "https://gum-gum-streaming.com/eyeshield-21-vostfr/",
        "episode_name": "• Épisode 145: Jouons tous au foot américain! YA HA!",
        "episode_url": "https://gum-gum-streaming.com/eyeshield-21-145-vostfr/"
    },
    {
        "episode_id": "bdbc37a8-ea96-11eb-b437-8cc84b59ec7a",
        "anime_url": "https://gum-gum-streaming.com/eyeshield-21-vostfr/",
        "episode_name": "• OAV 1: Maboroshi no Golden Bowl",
        "episode_url": "https://gum-gum-streaming.com/eyeshield-21-oav-1-vostfr/"
    },
    {
        "episode_id": "bdbfe215-ea96-11eb-abe6-8cc84b59ec7a",
        "anime_url": "https://gum-gum-streaming.com/eyeshield-21-vostfr/",
        "episode_name": "• OAV 2: Jump Festa",
        "episode_url": "https://gum-gum-streaming.com/eyeshield-21-oav-2-vostfr/"
    }
]