[
    {
        "episode_id": "f33fe89f-ea9f-11eb-9e81-8cc84b59ec7a",
        "anime_url": "https://gum-gum-streaming.com/kobato-vostfr/",
        "episode_name": "• Épisode 1: Le souhait d’une jeune fille",
        "episode_url": "https://gum-gum-streaming.com/kobato-1-vostfr/"
    },
    {
        "episode_id": "f342c29b-ea9f-11eb-a86f-8cc84b59ec7a",
        "anime_url": "https://gum-gum-streaming.com/kobato-vostfr/",
        "episode_name": "• Épisode 2: L’éclat des étoiles de sucre",
        "episode_url": "https://gum-gum-streaming.com/kobato-2-vostfr/"
    },
    {
        "episode_id": "f345c964-ea9f-11eb-b448-8cc84b59ec7a",
        "anime_url": "https://gum-gum-streaming.com/kobato-vostfr/",
        "episode_name": "• Épisode 3: Le cadeau de la pluie",
        "episode_url": "https://gum-gum-streaming.com/kobato-3-vostfr/"
    },
    {
        "episode_id": "f348bbeb-ea9f-11eb-8210-8cc84b59ec7a",
        "anime_url": "https://gum-gum-streaming.com/kobato-vostfr/",
        "episode_name": "• Épisode 4: Le frémissement des feuilles",
        "episode_url": "https://gum-gum-streaming.com/kobato-4-vostfr/"
    },
    {
        "episode_id": "f34ba336-ea9f-11eb-a399-8cc84b59ec7a",
        "anime_url": "https://gum-gum-streaming.com/kobato-vostfr/",
        "episode_name": "• Épisode 5: La promesse",
        "episode_url": "https://gum-gum-streaming.com/kobato-5-vostfr/"
    },
    {
        "episode_id": "f34e88de-ea9f-11eb-920a-8cc84b59ec7a",
        "anime_url": "https://gum-gum-streaming.com/kobato-vostfr/",
        "episode_name": "• Épisode 6: Un petit cache-cache",
        "episode_url": "https://gum-gum-streaming.com/kobato-6-vostfr/"
    },
    {
        "episode_id": "f35280c1-ea9f-11eb-8bba-8cc84b59ec7a",
        "anime_url": "https://gum-gum-streaming.com/kobato-vostfr/",
        "episode_name": "• Épisode 7: Une gentille personne",
        "episode_url": "https://gum-gum-streaming.com/kobato-7-vostfr/"
    },
    {
        "episode_id": "f3560362-ea9f-11eb-bceb-8cc84b59ec7a",
        "anime_url": "https://gum-gum-streaming.com/kobato-vostfr/",
        "episode_name": "• Épisode 8: La berceuse du chaton",
        "episode_url": "https://gum-gum-streaming.com/kobato-8-vostfr/"
    },
    {
        "episode_id": "f359d42b-ea9f-11eb-a3a2-8cc84b59ec7a",
        "anime_url": "https://gum-gum-streaming.com/kobato-vostfr/",
        "episode_name": "• Épisode 9: Souvenirs d’été",
        "episode_url": "https://gum-gum-streaming.com/kobato-9-vostfr/"
    },
    {
        "episode_id": "f35db314-ea9f-11eb-9d13-8cc84b59ec7a",
        "anime_url": "https://gum-gum-streaming.com/kobato-vostfr/",
        "episode_name": "• Épisode 10: Le garçon et l’orgue",
        "episode_url": "https://gum-gum-streaming.com/kobato-10-vostfr/"
    },
    {
        "episode_id": "f3653038-ea9f-11eb-a9d2-8cc84b59ec7a",
        "anime_url": "https://gum-gum-streaming.com/kobato-vostfr/",
        "episode_name": "• Épisode 11: Kobato Hanato, Détective",
        "episode_url": "https://gum-gum-streaming.com/kobato-11-vostfr/"
    },
    {
        "episode_id": "f367a15e-ea9f-11eb-b0cd-8cc84b59ec7a",
        "anime_url": "https://gum-gum-streaming.com/kobato-vostfr/",
        "episode_name": "• Épisode 12: La prunelle argentée",
        "episode_url": "https://gum-gum-streaming.com/kobato-12-vostfr/"
    },
    {
        "episode_id": "f36a39a1-ea9f-11eb-b165-8cc84b59ec7a",
        "anime_url": "https://gum-gum-streaming.com/kobato-vostfr/",
        "episode_name": "• Épisode 13: Ange et gardien",
        "episode_url": "https://gum-gum-streaming.com/kobato-13-vostfr/"
    },
    {
        "episode_id": "f36caabc-ea9f-11eb-a901-8cc84b59ec7a",
        "anime_url": "https://gum-gum-streaming.com/kobato-vostfr/",
        "episode_name": "• Épisode 14: Recherches au crépuscule",
        "episode_url": "https://gum-gum-streaming.com/kobato-14-vostfr/"
    },
    {
        "episode_id": "f36f2035-ea9f-11eb-a773-8cc84b59ec7a",
        "anime_url": "https://gum-gum-streaming.com/kobato-vostfr/",
        "episode_name": "• Épisode 15: Un vœu dissimulé",
        "episode_url": "https://gum-gum-streaming.com/kobato-15-vostfr/"
    },
    {
        "episode_id": "f37169c6-ea9f-11eb-ad75-8cc84b59ec7a",
        "anime_url": "https://gum-gum-streaming.com/kobato-vostfr/",
        "episode_name": "• Épisode 16: Une étrange créature",
        "episode_url": "https://gum-gum-streaming.com/kobato-16-vostfr/"
    },
    {
        "episode_id": "f373d9de-ea9f-11eb-8b0c-8cc84b59ec7a",
        "anime_url": "https://gum-gum-streaming.com/kobato-vostfr/",
        "episode_name": "• Épisode 17: Une étrange créature n°2",
        "episode_url": "https://gum-gum-streaming.com/kobato-17-vostfr/"
    },
    {
        "episode_id": "f3765b18-ea9f-11eb-a6e5-8cc84b59ec7a",
        "anime_url": "https://gum-gum-streaming.com/kobato-vostfr/",
        "episode_name": "• Épisode 18: Chaleur et bise hivernale",
        "episode_url": "https://gum-gum-streaming.com/kobato-18-vostfr/"
    },
    {
        "episode_id": "f378f3a9-ea9f-11eb-a574-8cc84b59ec7a",
        "anime_url": "https://gum-gum-streaming.com/kobato-vostfr/",
        "episode_name": "• Épisode 19: Un Noël blanc",
        "episode_url": "https://gum-gum-streaming.com/kobato-19-vostfr/"
    },
    {
        "episode_id": "f37b8375-ea9f-11eb-9057-8cc84b59ec7a",
        "anime_url": "https://gum-gum-streaming.com/kobato-vostfr/",
        "episode_name": "• Épisode 20: Les voyageurs",
        "episode_url": "https://gum-gum-streaming.com/kobato-20-vostfr/"
    },
    {
        "episode_id": "f37e139c-ea9f-11eb-87a9-8cc84b59ec7a",
        "anime_url": "https://gum-gum-streaming.com/kobato-vostfr/",
        "episode_name": "• Épisode 21: Le retour du printemps",
        "episode_url": "https://gum-gum-streaming.com/kobato-21-vostfr/"
    },
    {
        "episode_id": "f3809f8d-ea9f-11eb-a4da-8cc84b59ec7a",
        "anime_url": "https://gum-gum-streaming.com/kobato-vostfr/",
        "episode_name": "• Épisode 22: Le jour des adieux",
        "episode_url": "https://gum-gum-streaming.com/kobato-22-vostfr/"
    },
    {
        "episode_id": "f383521b-ea9f-11eb-b78f-8cc84b59ec7a",
        "anime_url": "https://gum-gum-streaming.com/kobato-vostfr/",
        "episode_name": "• Épisode 23: Le souhait de Kobato",
        "episode_url": "https://gum-gum-streaming.com/kobato-23-vostfr/"
    },
    {
        "episode_id": "f38624c2-ea9f-11eb-ab3a-8cc84b59ec7a",
        "anime_url": "https://gum-gum-streaming.com/kobato-vostfr/",
        "episode_name": "• Épisode 24: Lendemain…",
        "episode_url": "https://gum-gum-streaming.com/kobato-24-vostfr/"
    },
    {
        "episode_id": "f38b8d73-ea9f-11eb-9cc0-8cc84b59ec7a",
        "anime_url": "https://gum-gum-streaming.com/kobato-vostfr/",
        "episode_name": "• Spécial 1:",
        "episode_url": "https://gum-gum-streaming.com/kobato-special-1-vostfr/"
    },
    {
        "episode_id": "f38e2973-ea9f-11eb-beeb-8cc84b59ec7a",
        "anime_url": "https://gum-gum-streaming.com/kobato-vostfr/",
        "episode_name": "• Spécial 2:",
        "episode_url": "https://gum-gum-streaming.com/kobato-special-2-vostfr/"
    },
    {
        "episode_id": "f390c1b8-ea9f-11eb-b8a7-8cc84b59ec7a",
        "anime_url": "https://gum-gum-streaming.com/kobato-vostfr/",
        "episode_name": "• Spécial 3:",
        "episode_url": "https://gum-gum-streaming.com/kobato-special-3-vostfr/"
    },
    {
        "episode_id": "f39344f7-ea9f-11eb-97f6-8cc84b59ec7a",
        "anime_url": "https://gum-gum-streaming.com/kobato-vostfr/",
        "episode_name": "• Spécial 4:",
        "episode_url": "https://gum-gum-streaming.com/kobato-special-4-vostfr/"
    },
    {
        "episode_id": "f39603a0-ea9f-11eb-acf0-8cc84b59ec7a",
        "anime_url": "https://gum-gum-streaming.com/kobato-vostfr/",
        "episode_name": "• Spécial 5:",
        "episode_url": "https://gum-gum-streaming.com/kobato-special-5-vostfr/"
    },
    {
        "episode_id": "f39938bf-ea9f-11eb-98d6-8cc84b59ec7a",
        "anime_url": "https://gum-gum-streaming.com/kobato-vostfr/",
        "episode_name": "• Spécial 6:",
        "episode_url": "https://gum-gum-streaming.com/kobato-special-6-vostfr/"
    },
    {
        "episode_id": "f39c1e79-ea9f-11eb-ad82-8cc84b59ec7a",
        "anime_url": "https://gum-gum-streaming.com/kobato-vostfr/",
        "episode_name": "• Spécial 7:",
        "episode_url": "https://gum-gum-streaming.com/kobato-special-7-vostfr/"
    },
    {
        "episode_id": "f39f2bd2-ea9f-11eb-9cf1-8cc84b59ec7a",
        "anime_url": "https://gum-gum-streaming.com/kobato-vostfr/",
        "episode_name": "• Spécial 8:",
        "episode_url": "https://gum-gum-streaming.com/kobato-special-8-vostfr/"
    }
]