[
    {
        "episode_id": "1e3222dd-ea9d-11eb-8931-8cc84b59ec7a",
        "anime_url": "https://gum-gum-streaming.com/joshi-kausei-vostfr/",
        "episode_name": "• Épisode 1: Momo et les lycéennes",
        "episode_url": "https://gum-gum-streaming.com/joshi-kausei-1-vostfr/"
    },
    {
        "episode_id": "1e34c910-ea9d-11eb-afe4-8cc84b59ec7a",
        "anime_url": "https://gum-gum-streaming.com/joshi-kausei-vostfr/",
        "episode_name": "• Épisode 2: Les lycéennes et le jour de poisse",
        "episode_url": "https://gum-gum-streaming.com/joshi-kausei-2-vostfr/"
    },
    {
        "episode_id": "1e372e70-ea9d-11eb-a4ef-8cc84b59ec7a",
        "anime_url": "https://gum-gum-streaming.com/joshi-kausei-vostfr/",
        "episode_name": "• Épisode 3: Les lycéennes face à la fatigue",
        "episode_url": "https://gum-gum-streaming.com/joshi-kausei-3-vostfr/"
    },
    {
        "episode_id": "1e39a266-ea9d-11eb-a610-8cc84b59ec7a",
        "anime_url": "https://gum-gum-streaming.com/joshi-kausei-vostfr/",
        "episode_name": "• Épisode 4: Les lycéennes vont au restau",
        "episode_url": "https://gum-gum-streaming.com/joshi-kausei-4-vostfr/"
    },
    {
        "episode_id": "1e3c7381-ea9d-11eb-a26e-8cc84b59ec7a",
        "anime_url": "https://gum-gum-streaming.com/joshi-kausei-vostfr/",
        "episode_name": "• Épisode 5: Les lycéennes et le skateboard",
        "episode_url": "https://gum-gum-streaming.com/joshi-kausei-5-vostfr/"
    },
    {
        "episode_id": "1e3ed7af-ea9d-11eb-851b-8cc84b59ec7a",
        "anime_url": "https://gum-gum-streaming.com/joshi-kausei-vostfr/",
        "episode_name": "• Épisode 6: Les lycéennes font de l’exercice",
        "episode_url": "https://gum-gum-streaming.com/joshi-kausei-6-vostfr/"
    },
    {
        "episode_id": "1e4142a9-ea9d-11eb-b159-8cc84b59ec7a",
        "anime_url": "https://gum-gum-streaming.com/joshi-kausei-vostfr/",
        "episode_name": "• Épisode 7: Les lycéennes et la buée",
        "episode_url": "https://gum-gum-streaming.com/joshi-kausei-7-vostfr/"
    },
    {
        "episode_id": "1e44441a-ea9d-11eb-a4a3-8cc84b59ec7a",
        "anime_url": "https://gum-gum-streaming.com/joshi-kausei-vostfr/",
        "episode_name": "• Épisode 8: Les lycéennes se mettent à l’abri",
        "episode_url": "https://gum-gum-streaming.com/joshi-kausei-8-vostfr/"
    },
    {
        "episode_id": "1e475247-ea9d-11eb-a302-8cc84b59ec7a",
        "anime_url": "https://gum-gum-streaming.com/joshi-kausei-vostfr/",
        "episode_name": "• Épisode 9: Les lycéennes et les ombres chinoises",
        "episode_url": "https://gum-gum-streaming.com/joshi-kausei-9-vostfr/"
    },
    {
        "episode_id": "1e4a8639-ea9d-11eb-b313-8cc84b59ec7a",
        "anime_url": "https://gum-gum-streaming.com/joshi-kausei-vostfr/",
        "episode_name": "• Épisode 10: Les lycéennes et la barrette",
        "episode_url": "https://gum-gum-streaming.com/joshi-kausei-10-vostfr/"
    },
    {
        "episode_id": "1e4d942e-ea9d-11eb-a223-8cc84b59ec7a",
        "anime_url": "https://gum-gum-streaming.com/joshi-kausei-vostfr/",
        "episode_name": "• Épisode 11: Les lycéennes et la table chauffante",
        "episode_url": "https://gum-gum-streaming.com/joshi-kausei-11-vostfr/"
    },
    {
        "episode_id": "1e50c8af-ea9d-11eb-9c10-8cc84b59ec7a",
        "anime_url": "https://gum-gum-streaming.com/joshi-kausei-vostfr/",
        "episode_name": "• Épisode 12: Les lycéennes sur le chemin du retour",
        "episode_url": "https://gum-gum-streaming.com/joshi-kausei-12-vostfr/"
    }
]