{
  "anime_id": 576,
  "anime_url": "https://gum-gum-streaming.com/higashi-no-eden-vostfr/",
  "anime_name": "Higashi no Eden VOSTFR",
  "anime_language": "VOSTFR",
  "anime_mean_rating": "4",
  "authors": "Kamiyama Kenji",
  "anime_type": "Shonen",
  "anime_kind": "Action, aventure, drame, psychologique, mystère, romance, thriller",
  "animation_studio": "Production I.G",
  "year_of_production": "2009",
  "n_episodes": "11",
  "status": "Terminé",
  "synopsis": "En 2010, dix missiles se sont abattus à travers tout le Japon sans faire la moindre victime. Trois mois après cette attaque, Misaki Mori une jeune étudiante en voyage scolaire aux Etats Unis pour la remise des diplôme se retrouve mêlée à une terrible affaire, elle est alors sauvée par un japonais amnésique du nom d’Akira Takizawa qui n’a sur lui qu’un téléphone et un fusil. De retour au Japon, un étrange message est envoyé sur le téléphone mobile de Takizawa tandis que le onzième missile est lancé contre Tokyo : 8,2 milliards de yens viennent de lui être versés…",
  "collect_date": "2021_07_22"
}