{
  "anime_id": 100,
  "anime_url": "https://gum-gum-streaming.com/araburu-kisetsu-no-otome-domo-yo-vostfr/",
  "anime_name": "Araburu Kisetsu no Otome-domo yo VOSTFR",
  "anime_language": "VOSTFR",
  "anime_mean_rating": "4.5",
  "authors": "Clamp",
  "anime_type": "Shonen",
  "anime_kind": "Drame, romance, tranche de vie, school life",
  "animation_studio": "Madhouse",
  "year_of_production": "2019",
  "n_episodes": "12",
  "status": "Terminé",
  "synopsis": "Nous suivons les relations sociales et sentimentales de 5 lycéennes membres du club de littérature. L’adolescence pousse chacune de ces filles, avec des antécédents et des personnalités différentes, à la découverte du sexe à travers leur cheminement drôle, douloureux et émotionnel vers l’âge adulte.",
  "collect_date": "2021_07_22"
}