{
  "anime_id": 459,
  "anime_url": "https://gum-gum-streaming.com/garo-honoo-no-kokuin-vostfr/",
  "anime_name": "Garo: Honoo no Kokuin VOSTFR",
  "anime_language": "VOSTFR",
  "anime_mean_rating": "5",
  "authors": "Amemiya Keita",
  "anime_type": "Shonen",
  "anime_kind": "Action, surnaturel, démons",
  "animation_studio": "Mappa",
  "year_of_production": "2014",
  "n_episodes": "25",
  "status": "Terminé",
  "synopsis": "L’histoire prend place dans le Royaume de Valiante, qui ressemble à l’Espagne au cours de l’inquisition espagnole. L’Ordre Makai est en pleine crise, le roi malade, manipulé par son vil conseiller Mendoza, lance une véritable chasse aux sorcières. Pendant cette chasse menaçant les chevaliers et prêtres Makai, une prêtresse enceinte est arrêtée et condamnée au bûcher. Alors que tout brûle, la prêtresse donne naissance à son fils en échange de sa vie. Le père de l’enfant, un chevalier Makai, brave les flammes et sauve son fils avant de disparaître. Bien des années plus tard, l’enfant est devenu un jeune homme de 17 ans nommé Leon Lewis, il détient maintenant l’armure d’or Garo. Mais pendant ce temps, Mendoza a étendu son influence permettant aux Horrors, créatures pouvant prendre une forme humaine pour mieux les manipuler et les manger, de s’insinuer un peu plus au gouvernement.",
  "collect_date": "2021_07_22"
}