{
  "anime_id": 1832,
  "anime_url": "https://gum-gum-streaming.com/final-fantasy-unlimited-vf/",
  "anime_name": "Final Fantasy Unlimited VF",
  "anime_language": "VF",
  "anime_mean_rating": "5",
  "authors": "Kawazu Akitoshi",
  "anime_type": "Shonen",
  "anime_kind": "Action, aventure, fantaisie, science-fiction, méchas",
  "animation_studio": "Gonzo",
  "year_of_production": "2001",
  "n_episodes": "25",
  "status": "Terminé",
  "synopsis": "L’histoire commença lorsque deux créatures divines (Léviathan et Bahamut) menèrent un combat acharné juste au dessus de la ville de Tokyo. La forte intensité de leur lutte créa un pilier obscur sur Terre qui inspira un sentiment de peur et de confusion dans la population. Les scientifiques chargés d’étudier cette colonne, Joe et Marie Hayakawa, se mirent à faire des recherches sur ce phénomène.",
  "collect_date": "2021_07_22"
}