{
  "anime_id": 9,
  "anime_url": "https://gum-gum-streaming.com/6-lovers-vostfr/",
  "anime_name": "6 Lovers VOSTFR",
  "anime_language": "VOSTFR",
  "anime_mean_rating": "5",
  "authors": "Hiroshi Kimura",
  "anime_type": "Josei",
  "anime_kind": "Comédie, drame, romance, amitié, surnaturel, yaoi, shonen-Ai",
  "animation_studio": "Dear+",
  "year_of_production": "2021",
  "n_episodes": "1",
  "status": "Terminé",
  "synopsis": "6 LOVERS contient 6 court-métrages : – Renai Ruby no Tadashī Furikata de Tanaka Ogeretsu – Kuroneko Kareshi de Aya Sakyo – ZE de Yuki Shimitsu – Ten Count de Rihito Takarai – Ameiro Paradox de Isaku Natsume – Seitokaichō ni Chūkoku de Kaori Monchi",
  "collect_date": "2021_07_22"
}