{
  "anime_id": 501,
  "anime_url": "https://gum-gum-streaming.com/granbelm-vostfr/",
  "anime_name": "Granbelm VOSTFR",
  "anime_language": "VOSTFR",
  "anime_mean_rating": "5",
  "authors": "Masaharu Watanabe",
  "anime_type": "Shonen",
  "anime_kind": "Drame, fantastique, romance, mythe, tranche de vie, school life",
  "animation_studio": "Nexus",
  "year_of_production": "2013",
  "n_episodes": "13",
  "status": "Terminé",
  "synopsis": "L’histoire prend place dans un monde où la magie, qui existait autrefois, est aujourd’hui devenue si faible que plus personne ne considère plus que son existence dans les contes. Mangetsu Kohinata, une lycéenne lambda, fait un jour la rencontre de Shingetsu Ernesta Fukami, une mystérieuse jeune fille qui vient d’arriver au Japon. Celle-ci dit venir d’Allemagne et elle a choisi une nuit de pleine Lune pour faire le voyage…",
  "collect_date": "2021_07_22"
}