{
  "anime_id": 874,
  "anime_url": "https://gum-gum-streaming.com/ladies-versus-butlers-vostfr/",
  "anime_name": "Ladies versus Butlers! VOSTFR",
  "anime_language": "VOSTFR",
  "anime_mean_rating": "4.6",
  "authors": "Kouzuki Tsukasa",
  "anime_type": "Shonen",
  "anime_kind": "Comédie, ecchi, romance, school life",
  "animation_studio": "Xebec",
  "year_of_production": "2010",
  "n_episodes": "12",
  "status": "Terminé",
  "synopsis": "L’histoire tourne autour d’une personne, Akiharu Hino, un jeune lyçéen, qui ressemble bien malgré lui à un jeune délinquant. Il s’inscrira dans une académie qui était à l’origine une école pour jeune fille, pour suivre un entrainement intensif. Les étudiants sont inscrits dans cette académie pour devenir des servantes (Maid) ou des domestiques (Butler).",
  "collect_date": "2021_07_22"
}