{
  "anime_id": 777,
  "anime_url": "https://gum-gum-streaming.com/keppeki-danshi-aoyama-kun-vostfr/",
  "anime_name": "Keppeki Danshi! Aoyama-kun VOSTFR",
  "anime_language": "VOSTFR",
  "anime_mean_rating": "4.5",
  "authors": "Taku Sakamoto",
  "anime_type": "Seinen",
  "anime_kind": "Comédie, sport",
  "animation_studio": "Studio Hibari",
  "year_of_production": "2017",
  "n_episodes": "12",
  "status": "Terminé",
  "synopsis": "Aoyama est un jeune génie du foot qui joue en milieu de terrain dans l’équipe nationale du Japon des moins de 16 ans. Mais ce garçon est un maniaque de la propreté, au point d’en être un véritable TOC : ses vêtements sont toujours parfaitement lavés, il met des gants pour faire une touche ou refuse de serrer la main transpirante de ses équipiers. Ainsi, son style de jeu s’est adapté à ses manies et déconcerte bien souvent ses adversaires…",
  "collect_date": "2021_07_22"
}