{
  "anime_id": 1590,
  "anime_url": "https://gum-gum-streaming.com/ultraviolet-code-044-vostfr/",
  "anime_name": "Ultraviolet: Code 044 VOSTFR",
  "anime_language": "VOSTFR",
  "anime_mean_rating": "5",
  "authors": "Osamu Dezaki",
  "anime_type": "Seinen",
  "anime_kind": "Action, science-fiction, surnaturel, vampires",
  "animation_studio": "Madhouse",
  "year_of_production": "2008",
  "n_episodes": "12",
  "status": "Terminé",
  "synopsis": "Le gouvernement a mis en place un projet qui consiste à modifier génétiquement les capacités des guerriers. Leur meilleur guerrière qui a pour code 044 est une femme qui a été génétiquement modifiée pour qu’elle soit plus rapide, plus forte et plus intelligente que ses adversaires mais en échange son espérance de vie diminue considérablement. Cependant lors d’une mission contre l’armée Pharge, elle rencontre Luke qui est un soldat de Pharge, elle se retrouve dans l’incapacité de le tuer. Ce qui va donc entrainer des conséquence, elle serra considérée comme une traitresse et sera la cible du Daxus Jr., le dirigeant du projet au sein du gouvernement.",
  "collect_date": "2021_07_22"
}