{
  "anime_id": 1505,
  "anime_url": "https://gum-gum-streaming.com/texhnolyze-vostfr/",
  "anime_name": "Texhnolyze VOSTFR",
  "anime_language": "VOSTFR",
  "anime_mean_rating": "5",
  "authors": "Hamasaki Hiroshi",
  "anime_type": "Seinen",
  "anime_kind": "Drame, science-fiction, psychologique, mystère",
  "animation_studio": "Madhouse",
  "year_of_production": "2003",
  "n_episodes": "22",
  "status": "Terminé",
  "synopsis": "La ville de Lux est en proie à une guerre intestine entre 3 clans : l’Organo, l’Alliance, et le Rakan. Tous luttent pour le contrôle de la rafia (plante servant à la ‘texhnolyzation’).Ichise, un boxeur et personnage principal de l’histoire, se verra amputer d’un bras et d’une jambe pour avoir désobéi à ses maîtres. Laissé pour mort, il sera ‘texhnolyzé’ (technologie qui remplace les membres perdus en les connectant au système nerveux) par une jeune scientifique. Mais Ichise, ne supportant pas la greffe, s’enfuira… Dans un même temps, un mysterieux individu (Yoshii) arrive en ville et observe ce qu’il s’y passe. Il rencontrera Ran, une fille capable de voir le futur proche. Inexorablement, les routes d’Ichise et Yoshii finiront par se croiser…",
  "collect_date": "2021_07_22"
}